Workbook

Sheet Inputs
B1: TERM LOAN / BORROWING — DURATION CALCULATOR
B2: Macaulay Duration | Modified Duration | DV01 | Convexity | Price Sensitivity
B4: LOAN PARAMETERS
B6: Principal (₹ Cr) | C6: 100 | D6: Loan notional
B7: Coupon Rate (% p.a.) | C7: 9.1 | D7: Nominal coupon — changes to coupon freq below
B8: Frequency (1=Yr, 2=Half, 4=Qtr) | C8: 2 | D8: Compounding periods per year
B9: Yield / YTM (% p.a.) | C9: 8.75 | D9: Market yield used for PV discounting
B10: Tenor (Years) | C10: 7 | D10: Loan maturity in years — can be fractional
B11: Start Date | C11: 46113 | D11: Loan drawdown / first coupon date
B12: Amortisation Type | C12: Bullet | D12: Bullet OR amortising (enter exactly: Bullet / Full / Partial)
B13: Partial Amort Rate (% principal/yr) | C13: 0 | D13: Only used if Type = Partial — % of principal repaid per year
B15: KEY OUTPUTS (LIVE — see Results Sheet)
B17: Macaulay Duration (Years) | C17: ='Results'!C8
B18: Modified Duration (Years) | C18: ='Results'!C9
B19: DV01 (₹ Cr per bp) | C19: ='Results'!C10
B20: Convexity | C20: ='Results'!C11
B21: Price per ₹100 face (₹) | C21: ='Results'!C12
B22: Modified Duration × Face Value | C22: ='Results'!C13
B23: Approx Price Change per 100bp up (₹ Cr) | C23: ='Results'!C14
B24: Approx Price Change per 100bp down (₹ Cr) | C24: ='Results'!C15
B26: NOTE: Change inputs (yellow cells) — all outputs update automatically. VBA What-If button on 'What-If' sheet runs Monte Carlo yield scenario simulation.

Sheet Cash Flows
B1: CASH FLOW SCHEDULE & DURATION CALCULATION | K1: 125
K2: 5
B3: Period | C3: Date | D3: Coupon (₹ Cr) | E3: Principal (₹ Cr) | F3: Total CF (₹ Cr) | G3: PV Factor | H3: PV of CF (₹ Cr) | I3: Weight × Time | K3: 120
B4: ← From Inputs sheet: | C4: Frequency: | D4: =Inputs!C8 | E4: Yield: | F4: =Inputs!C9 | G4: Tenor: | H4: =Inputs!C10
B5: 1 | C5: =DATE(YEAR(Inputs!C11),MONTH(Inputs!C11)+(1-1)*(12/Inputs!C8),DAY(Inputs!C11)) | D5: =IF(1<=Inputs!C10*Inputs!C8,Inputs!C6*Inputs!C7/Inputs!C8,0) | E5: =IF(Inputs!C12="Bullet",IF(1=Inputs!C10*Inputs!C8,IF(Inputs!C12="Bullet",Inputs!C6,0),0),IF(Inputs!C12="Full",IF(1<=Inputs!C10*Inputs!C8,Inputs!C6/(Inputs!C10*Inputs!C8),0),IF(1<=Inputs!C10*Inputs!C8,MAX(Inputs!C6*Inputs!C13/Inputs!C8-SUM($D$5:$D4),0),0))) | F5: =D5+E5 | G5: =IFERROR(1/(1+Inputs!C9/Inputs!C8)^1,"") | H5: =F5*G5
B6: 2 | C6: =DATE(YEAR(Inputs!C11),MONTH(Inputs!C11)+(2-1)*(12/Inputs!C8),DAY(Inputs!C11)) | D6: =IF(2<=Inputs!C10*Inputs!C8,Inputs!C6*Inputs!C7/Inputs!C8,0) | E6: =IF(Inputs!C12="Bullet",IF(2=Inputs!C10*Inputs!C8,IF(Inputs!C12="Bullet",Inputs!C6,0),0),IF(Inputs!C12="Full",IF(2<=Inputs!C10*Inputs!C8,Inputs!C6/(Inputs!C10*Inputs!C8),0),IF(2<=Inputs!C10*Inputs!C8,MAX(Inputs!C6*Inputs!C13/Inputs!C8-SUM($D$5:$D5),0),0))) | F6: =D6+E6 | G6: =IFERROR(1/(1+Inputs!C9/Inputs!C8)^2,"") | H6: =F6*G6
B7: 3 | C7: =DATE(YEAR(Inputs!C11),MONTH(Inputs!C11)+(3-1)*(12/Inputs!C8),DAY(Inputs!C11)) | D7: =IF(3<=Inputs!C10*Inputs!C8,Inputs!C6*Inputs!C7/Inputs!C8,0) | E7: =IF(Inputs!C12="Bullet",IF(3=Inputs!C10*Inputs!C8,IF(Inputs!C12="Bullet",Inputs!C6,0),0),IF(Inputs!C12="Full",IF(3<=Inputs!C10*Inputs!C8,Inputs!C6/(Inputs!C10*Inputs!C8),0),IF(3<=Inputs!C10*Inputs!C8,MAX(Inputs!C6*Inputs!C13/Inputs!C8-SUM($D$5:$D6),0),0))) | F7: =D7+E7 | G7: =IFERROR(1/(1+Inputs!C9/Inputs!C8)^3,"") | H7: =F7*G7
B8: 4 | C8: =DATE(YEAR(Inputs!C11),MONTH(Inputs!C11)+(4-1)*(12/Inputs!C8),DAY(Inputs!C11)) | D8: =IF(4<=Inputs!C10*Inputs!C8,Inputs!C6*Inputs!C7/Inputs!C8,0) | E8: =IF(Inputs!C12="Bullet",IF(4=Inputs!C10*Inputs!C8,IF(Inputs!C12="Bullet",Inputs!C6,0),0),IF(Inputs!C12="Full",IF(4<=Inputs!C10*Inputs!C8,Inputs!C6/(Inputs!C10*Inputs!C8),0),IF(4<=Inputs!C10*Inputs!C8,MAX(Inputs!C6*Inputs!C13/Inputs!C8-SUM($D$5:$D7),0),0))) | F8: =D8+E8 | G8: =IFERROR(1/(1+Inputs!C9/Inputs!C8)^4,"") | H8: =F8*G8
B9: 5 | C9: =DATE(YEAR(Inputs!C11),MONTH(Inputs!C11)+(5-1)*(12/Inputs!C8),DAY(Inputs!C11)) | D9: =IF(5<=Inputs!C10*Inputs!C8,Inputs!C6*Inputs!C7/Inputs!C8,0) | E9: =IF(Inputs!C12="Bullet",IF(5=Inputs!C10*Inputs!C8,IF(Inputs!C12="Bullet",Inputs!C6,0),0),IF(Inputs!C12="Full",IF(5<=Inputs!C10*Inputs!C8,Inputs!C6/(Inputs!C10*Inputs!C8),0),IF(5<=Inputs!C10*Inputs!C8,MAX(Inputs!C6*Inputs!C13/Inputs!C8-SUM($D$5:$D8),0),0))) | F9: =D9+E9 | G9: =IFERROR(1/(1+Inputs!C9/Inputs!C8)^5,"") | H9: =F9*G9
B10: 6 | C10: =DATE(YEAR(Inputs!C11),MONTH(Inputs!C11)+(6-1)*(12/Inputs!C8),DAY(Inputs!C11)) | D10: =IF(6<=Inputs!C10*Inputs!C8,Inputs!C6*Inputs!C7/Inputs!C8,0) | E10: =IF(Inputs!C12="Bullet",IF(6=Inputs!C10*Inputs!C8,IF(Inputs!C12="Bullet",Inputs!C6,0),0),IF(Inputs!C12="Full",IF(6<=Inputs!C10*Inputs!C8,Inputs!C6/(Inputs!C10*Inputs!C8),0),IF(6<=Inputs!C10*Inputs!C8,MAX(Inputs!C6*Inputs!C13/Inputs!C8-SUM($D$5:$D9),0),0))) | F10: =D10+E10 | G10: =IFERROR(1/(1+Inputs!C9/Inputs!C8)^6,"") | H10: =F10*G10
B11: 7 | C11: =DATE(YEAR(Inputs!C11),MONTH(Inputs!C11)+(7-1)*(12/Inputs!C8),DAY(Inputs!C11)) | D11: =IF(7<=Inputs!C10*Inputs!C8,Inputs!C6*Inputs!C7/Inputs!C8,0) | E11: =IF(Inputs!C12="Bullet",IF(7=Inputs!C10*Inputs!C8,IF(Inputs!C12="Bullet",Inputs!C6,0),0),IF(Inputs!C12="Full",IF(7<=Inputs!C10*Inputs!C8,Inputs!C6/(Inputs!C10*Inputs!C8),0),IF(7<=Inputs!C10*Inputs!C8,MAX(Inputs!C6*Inputs!C13/Inputs!C8-SUM($D$5:$D10),0),0))) | F11: =D11+E11 | G11: =IFERROR(1/(1+Inputs!C9/Inputs!C8)^7,"") | H11: =F11*G11
B12: 8 | C12: =DATE(YEAR(Inputs!C11),MONTH(Inputs!C11)+(8-1)*(12/Inputs!C8),DAY(Inputs!C11)) | D12: =IF(8<=Inputs!C10*Inputs!C8,Inputs!C6*Inputs!C7/Inputs!C8,0) | E12: =IF(Inputs!C12="Bullet",IF(8=Inputs!C10*Inputs!C8,IF(Inputs!C12="Bullet",Inputs!C6,0),0),IF(Inputs!C12="Full",IF(8<=Inputs!C10*Inputs!C8,Inputs!C6/(Inputs!C10*Inputs!C8),0),IF(8<=Inputs!C10*Inputs!C8,MAX(Inputs!C6*Inputs!C13/Inputs!C8-SUM($D$5:$D11),0),0))) | F12: =D12+E12 | G12: =IFERROR(1/(1+Inputs!C9/Inputs!C8)^8,"") | H12: =F12*G12
B13: 9 | C13: =DATE(YEAR(Inputs!C11),MONTH(Inputs!C11)+(9-1)*(12/Inputs!C8),DAY(Inputs!C11)) | D13: =IF(9<=Inputs!C10*Inputs!C8,Inputs!C6*Inputs!C7/Inputs!C8,0) | E13: =IF(Inputs!C12="Bullet",IF(9=Inputs!C10*Inputs!C8,IF(Inputs!C12="Bullet",Inputs!C6,0),0),IF(Inputs!C12="Full",IF(9<=Inputs!C10*Inputs!C8,Inputs!C6/(Inputs!C10*Inputs!C8),0),IF(9<=Inputs!C10*Inputs!C8,MAX(Inputs!C6*Inputs!C13/Inputs!C8-SUM($D$5:$D12),0),0))) | F13: =D13+E13 | G13: =IFERROR(1/(1+Inputs!C9/Inputs!C8)^9,"") | H13: =F13*G13
B14: 10 | C14: =DATE(YEAR(Inputs!C11),MONTH(Inputs!C11)+(10-1)*(12/Inputs!C8),DAY(Inputs!C11)) | D14: =IF(10<=Inputs!C10*Inputs!C8,Inputs!C6*Inputs!C7/Inputs!C8,0) | E14: =IF(Inputs!C12="Bullet",IF(10=Inputs!C10*Inputs!C8,IF(Inputs!C12="Bullet",Inputs!C6,0),0),IF(Inputs!C12="Full",IF(10<=Inputs!C10*Inputs!C8,Inputs!C6/(Inputs!C10*Inputs!C8),0),IF(10<=Inputs!C10*Inputs!C8,MAX(Inputs!C6*Inputs!C13/Inputs!C8-SUM($D$5:$D13),0),0))) | F14: =D14+E14 | G14: =IFERROR(1/(1+Inputs!C9/Inputs!C8)^10,"") | H14: =F14*G14
B15: 11 | C15: =DATE(YEAR(Inputs!C11),MONTH(Inputs!C11)+(11-1)*(12/Inputs!C8),DAY(Inputs!C11)) | D15: =IF(11<=Inputs!C10*Inputs!C8,Inputs!C6*Inputs!C7/Inputs!C8,0) | E15: =IF(Inputs!C12="Bullet",IF(11=Inputs!C10*Inputs!C8,IF(Inputs!C12="Bullet",Inputs!C6,0),0),IF(Inputs!C12="Full",IF(11<=Inputs!C10*Inputs!C8,Inputs!C6/(Inputs!C10*Inputs!C8),0),IF(11<=Inputs!C10*Inputs!C8,MAX(Inputs!C6*Inputs!C13/Inputs!C8-SUM($D$5:$D14),0),0))) | F15: =D15+E15 | G15: =IFERROR(1/(1+Inputs!C9/Inputs!C8)^11,"") | H15: =F15*G15
B16: 12 | C16: =DATE(YEAR(Inputs!C11),MONTH(Inputs!C11)+(12-1)*(12/Inputs!C8),DAY(Inputs!C11)) | D16: =IF(12<=Inputs!C10*Inputs!C8,Inputs!C6*Inputs!C7/Inputs!C8,0) | E16: =IF(Inputs!C12="Bullet",IF(12=Inputs!C10*Inputs!C8,IF(Inputs!C12="Bullet",Inputs!C6,0),0),IF(Inputs!C12="Full",IF(12<=Inputs!C10*Inputs!C8,Inputs!C6/(Inputs!C10*Inputs!C8),0),IF(12<=Inputs!C10*Inputs!C8,MAX(Inputs!C6*Inputs!C13/Inputs!C8-SUM($D$5:$D15),0),0))) | F16: =D16+E16 | G16: =IFERROR(1/(1+Inputs!C9/Inputs!C8)^12,"") | H16: =F16*G16
B17: 13 | C17: =DATE(YEAR(Inputs!C11),MONTH(Inputs!C11)+(13-1)*(12/Inputs!C8),DAY(Inputs!C11)) | D17: =IF(13<=Inputs!C10*Inputs!C8,Inputs!C6*Inputs!C7/Inputs!C8,0) | E17: =IF(Inputs!C12="Bullet",IF(13=Inputs!C10*Inputs!C8,IF(Inputs!C12="Bullet",Inputs!C6,0),0),IF(Inputs!C12="Full",IF(13<=Inputs!C10*Inputs!C8,Inputs!C6/(Inputs!C10*Inputs!C8),0),IF(13<=Inputs!C10*Inputs!C8,MAX(Inputs!C6*Inputs!C13/Inputs!C8-SUM($D$5:$D16),0),0))) | F17: =D17+E17 | G17: =IFERROR(1/(1+Inputs!C9/Inputs!C8)^13,"") | H17: =F17*G17
B18: 14 | C18: =DATE(YEAR(Inputs!C11),MONTH(Inputs!C11)+(14-1)*(12/Inputs!C8),DAY(Inputs!C11)) | D18: =IF(14<=Inputs!C10*Inputs!C8,Inputs!C6*Inputs!C7/Inputs!C8,0) | E18: =IF(Inputs!C12="Bullet",IF(14=Inputs!C10*Inputs!C8,IF(Inputs!C12="Bullet",Inputs!C6,0),0),IF(Inputs!C12="Full",IF(14<=Inputs!C10*Inputs!C8,Inputs!C6/(Inputs!C10*Inputs!C8),0),IF(14<=Inputs!C10*Inputs!C8,MAX(Inputs!C6*Inputs!C13/Inputs!C8-SUM($D$5:$D17),0),0))) | F18: =D18+E18 | G18: =IFERROR(1/(1+Inputs!C9/Inputs!C8)^14,"") | H18: =F18*G18
B19: 15 | C19: =DATE(YEAR(Inputs!C11),MONTH(Inputs!C11)+(15-1)*(12/Inputs!C8),DAY(Inputs!C11)) | D19: =IF(15<=Inputs!C10*Inputs!C8,Inputs!C6*Inputs!C7/Inputs!C8,0) | E19: =IF(Inputs!C12="Bullet",IF(15=Inputs!C10*Inputs!C8,IF(Inputs!C12="Bullet",Inputs!C6,0),0),IF(Inputs!C12="Full",IF(15<=Inputs!C10*Inputs!C8,Inputs!C6/(Inputs!C10*Inputs!C8),0),IF(15<=Inputs!C10*Inputs!C8,MAX(Inputs!C6*Inputs!C13/Inputs!C8-SUM($D$5:$D18),0),0))) | F19: =D19+E19 | G19: =IFERROR(1/(1+Inputs!C9/Inputs!C8)^15,"") | H19: =F19*G19
B20: 16 | C20: =DATE(YEAR(Inputs!C11),MONTH(Inputs!C11)+(16-1)*(12/Inputs!C8),DAY(Inputs!C11)) | D20: =IF(16<=Inputs!C10*Inputs!C8,Inputs!C6*Inputs!C7/Inputs!C8,0) | E20: =IF(Inputs!C12="Bullet",IF(16=Inputs!C10*Inputs!C8,IF(Inputs!C12="Bullet",Inputs!C6,0),0),IF(Inputs!C12="Full",IF(16<=Inputs!C10*Inputs!C8,Inputs!C6/(Inputs!C10*Inputs!C8),0),IF(16<=Inputs!C10*Inputs!C8,MAX(Inputs!C6*Inputs!C13/Inputs!C8-SUM($D$5:$D19),0),0))) | F20: =D20+E20 | G20: =IFERROR(1/(1+Inputs!C9/Inputs!C8)^16,"") | H20: =F20*G20
B21: 17 | C21: =DATE(YEAR(Inputs!C11),MONTH(Inputs!C11)+(17-1)*(12/Inputs!C8),DAY(Inputs!C11)) | D21: =IF(17<=Inputs!C10*Inputs!C8,Inputs!C6*Inputs!C7/Inputs!C8,0) | E21: =IF(Inputs!C12="Bullet",IF(17=Inputs!C10*Inputs!C8,IF(Inputs!C12="Bullet",Inputs!C6,0),0),IF(Inputs!C12="Full",IF(17<=Inputs!C10*Inputs!C8,Inputs!C6/(Inputs!C10*Inputs!C8),0),IF(17<=Inputs!C10*Inputs!C8,MAX(Inputs!C6*Inputs!C13/Inputs!C8-SUM($D$5:$D20),0),0))) | F21: =D21+E21 | G21: =IFERROR(1/(1+Inputs!C9/Inputs!C8)^17,"") | H21: =F21*G21
B22: 18 | C22: =DATE(YEAR(Inputs!C11),MONTH(Inputs!C11)+(18-1)*(12/Inputs!C8),DAY(Inputs!C11)) | D22: =IF(18<=Inputs!C10*Inputs!C8,Inputs!C6*Inputs!C7/Inputs!C8,0) | E22: =IF(Inputs!C12="Bullet",IF(18=Inputs!C10*Inputs!C8,IF(Inputs!C12="Bullet",Inputs!C6,0),0),IF(Inputs!C12="Full",IF(18<=Inputs!C10*Inputs!C8,Inputs!C6/(Inputs!C10*Inputs!C8),0),IF(18<=Inputs!C10*Inputs!C8,MAX(Inputs!C6*Inputs!C13/Inputs!C8-SUM($D$5:$D21),0),0))) | F22: =D22+E22 | G22: =IFERROR(1/(1+Inputs!C9/Inputs!C8)^18,"") | H22: =F22*G22
B23: 19 | C23: =DATE(YEAR(Inputs!C11),MONTH(Inputs!C11)+(19-1)*(12/Inputs!C8),DAY(Inputs!C11)) | D23: =IF(19<=Inputs!C10*Inputs!C8,Inputs!C6*Inputs!C7/Inputs!C8,0) | E23: =IF(Inputs!C12="Bullet",IF(19=Inputs!C10*Inputs!C8,IF(Inputs!C12="Bullet",Inputs!C6,0),0),IF(Inputs!C12="Full",IF(19<=Inputs!C10*Inputs!C8,Inputs!C6/(Inputs!C10*Inputs!C8),0),IF(19<=Inputs!C10*Inputs!C8,MAX(Inputs!C6*Inputs!C13/Inputs!C8-SUM($D$5:$D22),0),0))) | F23: =D23+E23 | G23: =IFERROR(1/(1+Inputs!C9/Inputs!C8)^19,"") | H23: =F23*G23
B24: 20 | C24: =DATE(YEAR(Inputs!C11),MONTH(Inputs!C11)+(20-1)*(12/Inputs!C8),DAY(Inputs!C11)) | D24: =IF(20<=Inputs!C10*Inputs!C8,Inputs!C6*Inputs!C7/Inputs!C8,0) | E24: =IF(Inputs!C12="Bullet",IF(20=Inputs!C10*Inputs!C8,IF(Inputs!C12="Bullet",Inputs!C6,0),0),IF(Inputs!C12="Full",IF(20<=Inputs!C10*Inputs!C8,Inputs!C6/(Inputs!C10*Inputs!C8),0),IF(20<=Inputs!C10*Inputs!C8,MAX(Inputs!C6*Inputs!C13/Inputs!C8-SUM($D$5:$D23),0),0))) | F24: =D24+E24 | G24: =IFERROR(1/(1+Inputs!C9/Inputs!C8)^20,"") | H24: =F24*G24
B25: 21 | C25: =DATE(YEAR(Inputs!C11),MONTH(Inputs!C11)+(21-1)*(12/Inputs!C8),DAY(Inputs!C11)) | D25: =IF(21<=Inputs!C10*Inputs!C8,Inputs!C6*Inputs!C7/Inputs!C8,0) | E25: =IF(Inputs!C12="Bullet",IF(21=Inputs!C10*Inputs!C8,IF(Inputs!C12="Bullet",Inputs!C6,0),0),IF(Inputs!C12="Full",IF(21<=Inputs!C10*Inputs!C8,Inputs!C6/(Inputs!C10*Inputs!C8),0),IF(21<=Inputs!C10*Inputs!C8,MAX(Inputs!C6*Inputs!C13/Inputs!C8-SUM($D$5:$D24),0),0))) | F25: =D25+E25 | G25: =IFERROR(1/(1+Inputs!C9/Inputs!C8)^21,"") | H25: =F25*G25
B26: 22 | C26: =DATE(YEAR(Inputs!C11),MONTH(Inputs!C11)+(22-1)*(12/Inputs!C8),DAY(Inputs!C11)) | D26: =IF(22<=Inputs!C10*Inputs!C8,Inputs!C6*Inputs!C7/Inputs!C8,0) | E26: =IF(Inputs!C12="Bullet",IF(22=Inputs!C10*Inputs!C8,IF(Inputs!C12="Bullet",Inputs!C6,0),0),IF(Inputs!C12="Full",IF(22<=Inputs!C10*Inputs!C8,Inputs!C6/(Inputs!C10*Inputs!C8),0),IF(22<=Inputs!C10*Inputs!C8,MAX(Inputs!C6*Inputs!C13/Inputs!C8-SUM($D$5:$D25),0),0))) | F26: =D26+E26 | G26: =IFERROR(1/(1+Inputs!C9/Inputs!C8)^22,"") | H26: =F26*G26
B27: 23 | C27: =DATE(YEAR(Inputs!C11),MONTH(Inputs!C11)+(23-1)*(12/Inputs!C8),DAY(Inputs!C11)) | D27: =IF(23<=Inputs!C10*Inputs!C8,Inputs!C6*Inputs!C7/Inputs!C8,0) | E27: =IF(Inputs!C12="Bullet",IF(23=Inputs!C10*Inputs!C8,IF(Inputs!C12="Bullet",Inputs!C6,0),0),IF(Inputs!C12="Full",IF(23<=Inputs!C10*Inputs!C8,Inputs!C6/(Inputs!C10*Inputs!C8),0),IF(23<=Inputs!C10*Inputs!C8,MAX(Inputs!C6*Inputs!C13/Inputs!C8-SUM($D$5:$D26),0),0))) | F27: =D27+E27 | G27: =IFERROR(1/(1+Inputs!C9/Inputs!C8)^23,"") | H27: =F27*G27
B28: 24 | C28: =DATE(YEAR(Inputs!C11),MONTH(Inputs!C11)+(24-1)*(12/Inputs!C8),DAY(Inputs!C11)) | D28: =IF(24<=Inputs!C10*Inputs!C8,Inputs!C6*Inputs!C7/Inputs!C8,0) | E28: =IF(Inputs!C12="Bullet",IF(24=Inputs!C10*Inputs!C8,IF(Inputs!C12="Bullet",Inputs!C6,0),0),IF(Inputs!C12="Full",IF(24<=Inputs!C10*Inputs!C8,Inputs!C6/(Inputs!C10*Inputs!C8),0),IF(24<=Inputs!C10*Inputs!C8,MAX(Inputs!C6*Inputs!C13/Inputs!C8-SUM($D$5:$D27),0),0))) | F28: =D28+E28 | G28: =IFERROR(1/(1+Inputs!C9/Inputs!C8)^24,"") | H28: =F28*G28
B29: 25 | C29: =DATE(YEAR(Inputs!C11),MONTH(Inputs!C11)+(25-1)*(12/Inputs!C8),DAY(Inputs!C11)) | D29: =IF(25<=Inputs!C10*Inputs!C8,Inputs!C6*Inputs!C7/Inputs!C8,0) | E29: =IF(Inputs!C12="Bullet",IF(25=Inputs!C10*Inputs!C8,IF(Inputs!C12="Bullet",Inputs!C6,0),0),IF(Inputs!C12="Full",IF(25<=Inputs!C10*Inputs!C8,Inputs!C6/(Inputs!C10*Inputs!C8),0),IF(25<=Inputs!C10*Inputs!C8,MAX(Inputs!C6*Inputs!C13/Inputs!C8-SUM($D$5:$D28),0),0))) | F29: =D29+E29 | G29: =IFERROR(1/(1+Inputs!C9/Inputs!C8)^25,"") | H29: =F29*G29
B30: 26 | C30: =DATE(YEAR(Inputs!C11),MONTH(Inputs!C11)+(26-1)*(12/Inputs!C8),DAY(Inputs!C11)) | D30: =IF(26<=Inputs!C10*Inputs!C8,Inputs!C6*Inputs!C7/Inputs!C8,0) | E30: =IF(Inputs!C12="Bullet",IF(26=Inputs!C10*Inputs!C8,IF(Inputs!C12="Bullet",Inputs!C6,0),0),IF(Inputs!C12="Full",IF(26<=Inputs!C10*Inputs!C8,Inputs!C6/(Inputs!C10*Inputs!C8),0),IF(26<=Inputs!C10*Inputs!C8,MAX(Inputs!C6*Inputs!C13/Inputs!C8-SUM($D$5:$D29),0),0))) | F30: =D30+E30 | G30: =IFERROR(1/(1+Inputs!C9/Inputs!C8)^26,"") | H30: =F30*G30
B31: 27 | C31: =DATE(YEAR(Inputs!C11),MONTH(Inputs!C11)+(27-1)*(12/Inputs!C8),DAY(Inputs!C11)) | D31: =IF(27<=Inputs!C10*Inputs!C8,Inputs!C6*Inputs!C7/Inputs!C8,0) | E31: =IF(Inputs!C12="Bullet",IF(27=Inputs!C10*Inputs!C8,IF(Inputs!C12="Bullet",Inputs!C6,0),0),IF(Inputs!C12="Full",IF(27<=Inputs!C10*Inputs!C8,Inputs!C6/(Inputs!C10*Inputs!C8),0),IF(27<=Inputs!C10*Inputs!C8,MAX(Inputs!C6*Inputs!C13/Inputs!C8-SUM($D$5:$D30),0),0))) | F31: =D31+E31 | G31: =IFERROR(1/(1+Inputs!C9/Inputs!C8)^27,"") | H31: =F31*G31
B32: 28 | C32: =DATE(YEAR(Inputs!C11),MONTH(Inputs!C11)+(28-1)*(12/Inputs!C8),DAY(Inputs!C11)) | D32: =IF(28<=Inputs!C10*Inputs!C8,Inputs!C6*Inputs!C7/Inputs!C8,0) | E32: =IF(Inputs!C12="Bullet",IF(28=Inputs!C10*Inputs!C8,IF(Inputs!C12="Bullet",Inputs!C6,0),0),IF(Inputs!C12="Full",IF(28<=Inputs!C10*Inputs!C8,Inputs!C6/(Inputs!C10*Inputs!C8),0),IF(28<=Inputs!C10*Inputs!C8,MAX(Inputs!C6*Inputs!C13/Inputs!C8-SUM($D$5:$D31),0),0))) | F32: =D32+E32 | G32: =IFERROR(1/(1+Inputs!C9/Inputs!C8)^28,"") | H32: =F32*G32
B33: 29 | C33: =DATE(YEAR(Inputs!C11),MONTH(Inputs!C11)+(29-1)*(12/Inputs!C8),DAY(Inputs!C11)) | D33: =IF(29<=Inputs!C10*Inputs!C8,Inputs!C6*Inputs!C7/Inputs!C8,0) | E33: =IF(Inputs!C12="Bullet",IF(29=Inputs!C10*Inputs!C8,IF(Inputs!C12="Bullet",Inputs!C6,0),0),IF(Inputs!C12="Full",IF(29<=Inputs!C10*Inputs!C8,Inputs!C6/(Inputs!C10*Inputs!C8),0),IF(29<=Inputs!C10*Inputs!C8,MAX(Inputs!C6*Inputs!C13/Inputs!C8-SUM($D$5:$D32),0),0))) | F33: =D33+E33 | G33: =IFERROR(1/(1+Inputs!C9/Inputs!C8)^29,"") | H33: =F33*G33
B34: 30 | C34: =DATE(YEAR(Inputs!C11),MONTH(Inputs!C11)+(30-1)*(12/Inputs!C8),DAY(Inputs!C11)) | D34: =IF(30<=Inputs!C10*Inputs!C8,Inputs!C6*Inputs!C7/Inputs!C8,0) | E34: =IF(Inputs!C12="Bullet",IF(30=Inputs!C10*Inputs!C8,IF(Inputs!C12="Bullet",Inputs!C6,0),0),IF(Inputs!C12="Full",IF(30<=Inputs!C10*Inputs!C8,Inputs!C6/(Inputs!C10*Inputs!C8),0),IF(30<=Inputs!C10*Inputs!C8,MAX(Inputs!C6*Inputs!C13/Inputs!C8-SUM($D$5:$D33),0),0))) | F34: =D34+E34 | G34: =IFERROR(1/(1+Inputs!C9/Inputs!C8)^30,"") | H34: =F34*G34
B35: 31 | C35: =DATE(YEAR(Inputs!C11),MONTH(Inputs!C11)+(31-1)*(12/Inputs!C8),DAY(Inputs!C11)) | D35: =IF(31<=Inputs!C10*Inputs!C8,Inputs!C6*Inputs!C7/Inputs!C8,0) | E35: =IF(Inputs!C12="Bullet",IF(31=Inputs!C10*Inputs!C8,IF(Inputs!C12="Bullet",Inputs!C6,0),0),IF(Inputs!C12="Full",IF(31<=Inputs!C10*Inputs!C8,Inputs!C6/(Inputs!C10*Inputs!C8),0),IF(31<=Inputs!C10*Inputs!C8,MAX(Inputs!C6*Inputs!C13/Inputs!C8-SUM($D$5:$D34),0),0))) | F35: =D35+E35 | G35: =IFERROR(1/(1+Inputs!C9/Inputs!C8)^31,"") | H35: =F35*G35
B36: 32 | C36: =DATE(YEAR(Inputs!C11),MONTH(Inputs!C11)+(32-1)*(12/Inputs!C8),DAY(Inputs!C11)) | D36: =IF(32<=Inputs!C10*Inputs!C8,Inputs!C6*Inputs!C7/Inputs!C8,0) | E36: =IF(Inputs!C12="Bullet",IF(32=Inputs!C10*Inputs!C8,IF(Inputs!C12="Bullet",Inputs!C6,0),0),IF(Inputs!C12="Full",IF(32<=Inputs!C10*Inputs!C8,Inputs!C6/(Inputs!C10*Inputs!C8),0),IF(32<=Inputs!C10*Inputs!C8,MAX(Inputs!C6*Inputs!C13/Inputs!C8-SUM($D$5:$D35),0),0))) | F36: =D36+E36 | G36: =IFERROR(1/(1+Inputs!C9/Inputs!C8)^32,"") | H36: =F36*G36
B37: 33 | C37: =DATE(YEAR(Inputs!C11),MONTH(Inputs!C11)+(33-1)*(12/Inputs!C8),DAY(Inputs!C11)) | D37: =IF(33<=Inputs!C10*Inputs!C8,Inputs!C6*Inputs!C7/Inputs!C8,0) | E37: =IF(Inputs!C12="Bullet",IF(33=Inputs!C10*Inputs!C8,IF(Inputs!C12="Bullet",Inputs!C6,0),0),IF(Inputs!C12="Full",IF(33<=Inputs!C10*Inputs!C8,Inputs!C6/(Inputs!C10*Inputs!C8),0),IF(33<=Inputs!C10*Inputs!C8,MAX(Inputs!C6*Inputs!C13/Inputs!C8-SUM($D$5:$D36),0),0))) | F37: =D37+E37 | G37: =IFERROR(1/(1+Inputs!C9/Inputs!C8)^33,"") | H37: =F37*G37
B38: 34 | C38: =DATE(YEAR(Inputs!C11),MONTH(Inputs!C11)+(34-1)*(12/Inputs!C8),DAY(Inputs!C11)) | D38: =IF(34<=Inputs!C10*Inputs!C8,Inputs!C6*Inputs!C7/Inputs!C8,0) | E38: =IF(Inputs!C12="Bullet",IF(34=Inputs!C10*Inputs!C8,IF(Inputs!C12="Bullet",Inputs!C6,0),0),IF(Inputs!C12="Full",IF(34<=Inputs!C10*Inputs!C8,Inputs!C6/(Inputs!C10*Inputs!C8),0),IF(34<=Inputs!C10*Inputs!C8,MAX(Inputs!C6*Inputs!C13/Inputs!C8-SUM($D$5:$D37),0),0))) | F38: =D38+E38 | G38: =IFERROR(1/(1+Inputs!C9/Inputs!C8)^34,"") | H38: =F38*G38
B39: 35 | C39: =DATE(YEAR(Inputs!C11),MONTH(Inputs!C11)+(35-1)*(12/Inputs!C8),DAY(Inputs!C11)) | D39: =IF(35<=Inputs!C10*Inputs!C8,Inputs!C6*Inputs!C7/Inputs!C8,0) | E39: =IF(Inputs!C12="Bullet",IF(35=Inputs!C10*Inputs!C8,IF(Inputs!C12="Bullet",Inputs!C6,0),0),IF(Inputs!C12="Full",IF(35<=Inputs!C10*Inputs!C8,Inputs!C6/(Inputs!C10*Inputs!C8),0),IF(35<=Inputs!C10*Inputs!C8,MAX(Inputs!C6*Inputs!C13/Inputs!C8-SUM($D$5:$D38),0),0))) | F39: =D39+E39 | G39: =IFERROR(1/(1+Inputs!C9/Inputs!C8)^35,"") | H39: =F39*G39
B40: 36 | C40: =DATE(YEAR(Inputs!C11),MONTH(Inputs!C11)+(36-1)*(12/Inputs!C8),DAY(Inputs!C11)) | D40: =IF(36<=Inputs!C10*Inputs!C8,Inputs!C6*Inputs!C7/Inputs!C8,0) | E40: =IF(Inputs!C12="Bullet",IF(36=Inputs!C10*Inputs!C8,IF(Inputs!C12="Bullet",Inputs!C6,0),0),IF(Inputs!C12="Full",IF(36<=Inputs!C10*Inputs!C8,Inputs!C6/(Inputs!C10*Inputs!C8),0),IF(36<=Inputs!C10*Inputs!C8,MAX(Inputs!C6*Inputs!C13/Inputs!C8-SUM($D$5:$D39),0),0))) | F40: =D40+E40 | G40: =IFERROR(1/(1+Inputs!C9/Inputs!C8)^36,"") | H40: =F40*G40
B41: 37 | C41: =DATE(YEAR(Inputs!C11),MONTH(Inputs!C11)+(37-1)*(12/Inputs!C8),DAY(Inputs!C11)) | D41: =IF(37<=Inputs!C10*Inputs!C8,Inputs!C6*Inputs!C7/Inputs!C8,0) | E41: =IF(Inputs!C12="Bullet",IF(37=Inputs!C10*Inputs!C8,IF(Inputs!C12="Bullet",Inputs!C6,0),0),IF(Inputs!C12="Full",IF(37<=Inputs!C10*Inputs!C8,Inputs!C6/(Inputs!C10*Inputs!C8),0),IF(37<=Inputs!C10*Inputs!C8,MAX(Inputs!C6*Inputs!C13/Inputs!C8-SUM($D$5:$D40),0),0))) | F41: =D41+E41 | G41: =IFERROR(1/(1+Inputs!C9/Inputs!C8)^37,"") | H41: =F41*G41
B42: 38 | C42: =DATE(YEAR(Inputs!C11),MONTH(Inputs!C11)+(38-1)*(12/Inputs!C8),DAY(Inputs!C11)) | D42: =IF(38<=Inputs!C10*Inputs!C8,Inputs!C6*Inputs!C7/Inputs!C8,0) | E42: =IF(Inputs!C12="Bullet",IF(38=Inputs!C10*Inputs!C8,IF(Inputs!C12="Bullet",Inputs!C6,0),0),IF(Inputs!C12="Full",IF(38<=Inputs!C10*Inputs!C8,Inputs!C6/(Inputs!C10*Inputs!C8),0),IF(38<=Inputs!C10*Inputs!C8,MAX(Inputs!C6*Inputs!C13/Inputs!C8-SUM($D$5:$D41),0),0))) | F42: =D42+E42 | G42: =IFERROR(1/(1+Inputs!C9/Inputs!C8)^38,"") | H42: =F42*G42
B43: 39 | C43: =DATE(YEAR(Inputs!C11),MONTH(Inputs!C11)+(39-1)*(12/Inputs!C8),DAY(Inputs!C11)) | D43: =IF(39<=Inputs!C10*Inputs!C8,Inputs!C6*Inputs!C7/Inputs!C8,0) | E43: =IF(Inputs!C12="Bullet",IF(39=Inputs!C10*Inputs!C8,IF(Inputs!C12="Bullet",Inputs!C6,0),0),IF(Inputs!C12="Full",IF(39<=Inputs!C10*Inputs!C8,Inputs!C6/(Inputs!C10*Inputs!C8),0),IF(39<=Inputs!C10*Inputs!C8,MAX(Inputs!C6*Inputs!C13/Inputs!C8-SUM($D$5:$D42),0),0))) | F43: =D43+E43 | G43: =IFERROR(1/(1+Inputs!C9/Inputs!C8)^39,"") | H43: =F43*G43
B44: 40 | C44: =DATE(YEAR(Inputs!C11),MONTH(Inputs!C11)+(40-1)*(12/Inputs!C8),DAY(Inputs!C11)) | D44: =IF(40<=Inputs!C10*Inputs!C8,Inputs!C6*Inputs!C7/Inputs!C8,0) | E44: =IF(Inputs!C12="Bullet",IF(40=Inputs!C10*Inputs!C8,IF(Inputs!C12="Bullet",Inputs!C6,0),0),IF(Inputs!C12="Full",IF(40<=Inputs!C10*Inputs!C8,Inputs!C6/(Inputs!C10*Inputs!C8),0),IF(40<=Inputs!C10*Inputs!C8,MAX(Inputs!C6*Inputs!C13/Inputs!C8-SUM($D$5:$D43),0),0))) | F44: =D44+E44 | G44: =IFERROR(1/(1+Inputs!C9/Inputs!C8)^40,"") | H44: =F44*G44
B45: 41 | C45: =DATE(YEAR(Inputs!C11),MONTH(Inputs!C11)+(41-1)*(12/Inputs!C8),DAY(Inputs!C11)) | D45: =IF(41<=Inputs!C10*Inputs!C8,Inputs!C6*Inputs!C7/Inputs!C8,0) | E45: =IF(Inputs!C12="Bullet",IF(41=Inputs!C10*Inputs!C8,IF(Inputs!C12="Bullet",Inputs!C6,0),0),IF(Inputs!C12="Full",IF(41<=Inputs!C10*Inputs!C8,Inputs!C6/(Inputs!C10*Inputs!C8),0),IF(41<=Inputs!C10*Inputs!C8,MAX(Inputs!C6*Inputs!C13/Inputs!C8-SUM($D$5:$D44),0),0))) | F45: =D45+E45 | G45: =IFERROR(1/(1+Inputs!C9/Inputs!C8)^41,"") | H45: =F45*G45
B46: 42 | C46: =DATE(YEAR(Inputs!C11),MONTH(Inputs!C11)+(42-1)*(12/Inputs!C8),DAY(Inputs!C11)) | D46: =IF(42<=Inputs!C10*Inputs!C8,Inputs!C6*Inputs!C7/Inputs!C8,0) | E46: =IF(Inputs!C12="Bullet",IF(42=Inputs!C10*Inputs!C8,IF(Inputs!C12="Bullet",Inputs!C6,0),0),IF(Inputs!C12="Full",IF(42<=Inputs!C10*Inputs!C8,Inputs!C6/(Inputs!C10*Inputs!C8),0),IF(42<=Inputs!C10*Inputs!C8,MAX(Inputs!C6*Inputs!C13/Inputs!C8-SUM($D$5:$D45),0),0))) | F46: =D46+E46 | G46: =IFERROR(1/(1+Inputs!C9/Inputs!C8)^42,"") | H46: =F46*G46
B47: 43 | C47: =DATE(YEAR(Inputs!C11),MONTH(Inputs!C11)+(43-1)*(12/Inputs!C8),DAY(Inputs!C11)) | D47: =IF(43<=Inputs!C10*Inputs!C8,Inputs!C6*Inputs!C7/Inputs!C8,0) | E47: =IF(Inputs!C12="Bullet",IF(43=Inputs!C10*Inputs!C8,IF(Inputs!C12="Bullet",Inputs!C6,0),0),IF(Inputs!C12="Full",IF(43<=Inputs!C10*Inputs!C8,Inputs!C6/(Inputs!C10*Inputs!C8),0),IF(43<=Inputs!C10*Inputs!C8,MAX(Inputs!C6*Inputs!C13/Inputs!C8-SUM($D$5:$D46),0),0))) | F47: =D47+E47 | G47: =IFERROR(1/(1+Inputs!C9/Inputs!C8)^43,"") | H47: =F47*G47
B48: 44 | C48: =DATE(YEAR(Inputs!C11),MONTH(Inputs!C11)+(44-1)*(12/Inputs!C8),DAY(Inputs!C11)) | D48: =IF(44<=Inputs!C10*Inputs!C8,Inputs!C6*Inputs!C7/Inputs!C8,0) | E48: =IF(Inputs!C12="Bullet",IF(44=Inputs!C10*Inputs!C8,IF(Inputs!C12="Bullet",Inputs!C6,0),0),IF(Inputs!C12="Full",IF(44<=Inputs!C10*Inputs!C8,Inputs!C6/(Inputs!C10*Inputs!C8),0),IF(44<=Inputs!C10*Inputs!C8,MAX(Inputs!C6*Inputs!C13/Inputs!C8-SUM($D$5:$D47),0),0))) | F48: =D48+E48 | G48: =IFERROR(1/(1+Inputs!C9/Inputs!C8)^44,"") | H48: =F48*G48
B49: 45 | C49: =DATE(YEAR(Inputs!C11),MONTH(Inputs!C11)+(45-1)*(12/Inputs!C8),DAY(Inputs!C11)) | D49: =IF(45<=Inputs!C10*Inputs!C8,Inputs!C6*Inputs!C7/Inputs!C8,0) | E49: =IF(Inputs!C12="Bullet",IF(45=Inputs!C10*Inputs!C8,IF(Inputs!C12="Bullet",Inputs!C6,0),0),IF(Inputs!C12="Full",IF(45<=Inputs!C10*Inputs!C8,Inputs!C6/(Inputs!C10*Inputs!C8),0),IF(45<=Inputs!C10*Inputs!C8,MAX(Inputs!C6*Inputs!C13/Inputs!C8-SUM($D$5:$D48),0),0))) | F49: =D49+E49 | G49: =IFERROR(1/(1+Inputs!C9/Inputs!C8)^45,"") | H49: =F49*G49
B50: 46 | C50: =DATE(YEAR(Inputs!C11),MONTH(Inputs!C11)+(46-1)*(12/Inputs!C8),DAY(Inputs!C11)) | D50: =IF(46<=Inputs!C10*Inputs!C8,Inputs!C6*Inputs!C7/Inputs!C8,0) | E50: =IF(Inputs!C12="Bullet",IF(46=Inputs!C10*Inputs!C8,IF(Inputs!C12="Bullet",Inputs!C6,0),0),IF(Inputs!C12="Full",IF(46<=Inputs!C10*Inputs!C8,Inputs!C6/(Inputs!C10*Inputs!C8),0),IF(46<=Inputs!C10*Inputs!C8,MAX(Inputs!C6*Inputs!C13/Inputs!C8-SUM($D$5:$D49),0),0))) | F50: =D50+E50 | G50: =IFERROR(1/(1+Inputs!C9/Inputs!C8)^46,"") | H50: =F50*G50
B51: 47 | C51: =DATE(YEAR(Inputs!C11),MONTH(Inputs!C11)+(47-1)*(12/Inputs!C8),DAY(Inputs!C11)) | D51: =IF(47<=Inputs!C10*Inputs!C8,Inputs!C6*Inputs!C7/Inputs!C8,0) | E51: =IF(Inputs!C12="Bullet",IF(47=Inputs!C10*Inputs!C8,IF(Inputs!C12="Bullet",Inputs!C6,0),0),IF(Inputs!C12="Full",IF(47<=Inputs!C10*Inputs!C8,Inputs!C6/(Inputs!C10*Inputs!C8),0),IF(47<=Inputs!C10*Inputs!C8,MAX(Inputs!C6*Inputs!C13/Inputs!C8-SUM($D$5:$D50),0),0))) | F51: =D51+E51 | G51: =IFERROR(1/(1+Inputs!C9/Inputs!C8)^47,"") | H51: =F51*G51
B52: 48 | C52: =DATE(YEAR(Inputs!C11),MONTH(Inputs!C11)+(48-1)*(12/Inputs!C8),DAY(Inputs!C11)) | D52: =IF(48<=Inputs!C10*Inputs!C8,Inputs!C6*Inputs!C7/Inputs!C8,0) | E52: =IF(Inputs!C12="Bullet",IF(48=Inputs!C10*Inputs!C8,IF(Inputs!C12="Bullet",Inputs!C6,0),0),IF(Inputs!C12="Full",IF(48<=Inputs!C10*Inputs!C8,Inputs!C6/(Inputs!C10*Inputs!C8),0),IF(48<=Inputs!C10*Inputs!C8,MAX(Inputs!C6*Inputs!C13/Inputs!C8-SUM($D$5:$D51),0),0))) | F52: =D52+E52 | G52: =IFERROR(1/(1+Inputs!C9/Inputs!C8)^48,"") | H52: =F52*G52
B53: 49 | C53: =DATE(YEAR(Inputs!C11),MONTH(Inputs!C11)+(49-1)*(12/Inputs!C8),DAY(Inputs!C11)) | D53: =IF(49<=Inputs!C10*Inputs!C8,Inputs!C6*Inputs!C7/Inputs!C8,0) | E53: =IF(Inputs!C12="Bullet",IF(49=Inputs!C10*Inputs!C8,IF(Inputs!C12="Bullet",Inputs!C6,0),0),IF(Inputs!C12="Full",IF(49<=Inputs!C10*Inputs!C8,Inputs!C6/(Inputs!C10*Inputs!C8),0),IF(49<=Inputs!C10*Inputs!C8,MAX(Inputs!C6*Inputs!C13/Inputs!C8-SUM($D$5:$D52),0),0))) | F53: =D53+E53 | G53: =IFERROR(1/(1+Inputs!C9/Inputs!C8)^49,"") | H53: =F53*G53
B54: 50 | C54: =DATE(YEAR(Inputs!C11),MONTH(Inputs!C11)+(50-1)*(12/Inputs!C8),DAY(Inputs!C11)) | D54: =IF(50<=Inputs!C10*Inputs!C8,Inputs!C6*Inputs!C7/Inputs!C8,0) | E54: =IF(Inputs!C12="Bullet",IF(50=Inputs!C10*Inputs!C8,IF(Inputs!C12="Bullet",Inputs!C6,0),0),IF(Inputs!C12="Full",IF(50<=Inputs!C10*Inputs!C8,Inputs!C6/(Inputs!C10*Inputs!C8),0),IF(50<=Inputs!C10*Inputs!C8,MAX(Inputs!C6*Inputs!C13/Inputs!C8-SUM($D$5:$D53),0),0))) | F54: =D54+E54 | G54: =IFERROR(1/(1+Inputs!C9/Inputs!C8)^50,"") | H54: =F54*G54
B55: 51 | C55: =DATE(YEAR(Inputs!C11),MONTH(Inputs!C11)+(51-1)*(12/Inputs!C8),DAY(Inputs!C11)) | D55: =IF(51<=Inputs!C10*Inputs!C8,Inputs!C6*Inputs!C7/Inputs!C8,0) | E55: =IF(Inputs!C12="Bullet",IF(51=Inputs!C10*Inputs!C8,IF(Inputs!C12="Bullet",Inputs!C6,0),0),IF(Inputs!C12="Full",IF(51<=Inputs!C10*Inputs!C8,Inputs!C6/(Inputs!C10*Inputs!C8),0),IF(51<=Inputs!C10*Inputs!C8,MAX(Inputs!C6*Inputs!C13/Inputs!C8-SUM($D$5:$D54),0),0))) | F55: =D55+E55 | G55: =IFERROR(1/(1+Inputs!C9/Inputs!C8)^51,"") | H55: =F55*G55
B56: 52 | C56: =DATE(YEAR(Inputs!C11),MONTH(Inputs!C11)+(52-1)*(12/Inputs!C8),DAY(Inputs!C11)) | D56: =IF(52<=Inputs!C10*Inputs!C8,Inputs!C6*Inputs!C7/Inputs!C8,0) | E56: =IF(Inputs!C12="Bullet",IF(52=Inputs!C10*Inputs!C8,IF(Inputs!C12="Bullet",Inputs!C6,0),0),IF(Inputs!C12="Full",IF(52<=Inputs!C10*Inputs!C8,Inputs!C6/(Inputs!C10*Inputs!C8),0),IF(52<=Inputs!C10*Inputs!C8,MAX(Inputs!C6*Inputs!C13/Inputs!C8-SUM($D$5:$D55),0),0))) | F56: =D56+E56 | G56: =IFERROR(1/(1+Inputs!C9/Inputs!C8)^52,"") | H56: =F56*G56
B57: 53 | C57: =DATE(YEAR(Inputs!C11),MONTH(Inputs!C11)+(53-1)*(12/Inputs!C8),DAY(Inputs!C11)) | D57: =IF(53<=Inputs!C10*Inputs!C8,Inputs!C6*Inputs!C7/Inputs!C8,0) | E57: =IF(Inputs!C12="Bullet",IF(53=Inputs!C10*Inputs!C8,IF(Inputs!C12="Bullet",Inputs!C6,0),0),IF(Inputs!C12="Full",IF(53<=Inputs!C10*Inputs!C8,Inputs!C6/(Inputs!C10*Inputs!C8),0),IF(53<=Inputs!C10*Inputs!C8,MAX(Inputs!C6*Inputs!C13/Inputs!C8-SUM($D$5:$D56),0),0))) | F57: =D57+E57 | G57: =IFERROR(1/(1+Inputs!C9/Inputs!C8)^53,"") | H57: =F57*G57
B58: 54 | C58: =DATE(YEAR(Inputs!C11),MONTH(Inputs!C11)+(54-1)*(12/Inputs!C8),DAY(Inputs!C11)) | D58: =IF(54<=Inputs!C10*Inputs!C8,Inputs!C6*Inputs!C7/Inputs!C8,0) | E58: =IF(Inputs!C12="Bullet",IF(54=Inputs!C10*Inputs!C8,IF(Inputs!C12="Bullet",Inputs!C6,0),0),IF(Inputs!C12="Full",IF(54<=Inputs!C10*Inputs!C8,Inputs!C6/(Inputs!C10*Inputs!C8),0),IF(54<=Inputs!C10*Inputs!C8,MAX(Inputs!C6*Inputs!C13/Inputs!C8-SUM($D$5:$D57),0),0))) | F58: =D58+E58 | G58: =IFERROR(1/(1+Inputs!C9/Inputs!C8)^54,"") | H58: =F58*G58
B59: 55 | C59: =DATE(YEAR(Inputs!C11),MONTH(Inputs!C11)+(55-1)*(12/Inputs!C8),DAY(Inputs!C11)) | D59: =IF(55<=Inputs!C10*Inputs!C8,Inputs!C6*Inputs!C7/Inputs!C8,0) | E59: =IF(Inputs!C12="Bullet",IF(55=Inputs!C10*Inputs!C8,IF(Inputs!C12="Bullet",Inputs!C6,0),0),IF(Inputs!C12="Full",IF(55<=Inputs!C10*Inputs!C8,Inputs!C6/(Inputs!C10*Inputs!C8),0),IF(55<=Inputs!C10*Inputs!C8,MAX(Inputs!C6*Inputs!C13/Inputs!C8-SUM($D$5:$D58),0),0))) | F59: =D59+E59 | G59: =IFERROR(1/(1+Inputs!C9/Inputs!C8)^55,"") | H59: =F59*G59
B60: 56 | C60: =DATE(YEAR(Inputs!C11),MONTH(Inputs!C11)+(56-1)*(12/Inputs!C8),DAY(Inputs!C11)) | D60: =IF(56<=Inputs!C10*Inputs!C8,Inputs!C6*Inputs!C7/Inputs!C8,0) | E60: =IF(Inputs!C12="Bullet",IF(56=Inputs!C10*Inputs!C8,IF(Inputs!C12="Bullet",Inputs!C6,0),0),IF(Inputs!C12="Full",IF(56<=Inputs!C10*Inputs!C8,Inputs!C6/(Inputs!C10*Inputs!C8),0),IF(56<=Inputs!C10*Inputs!C8,MAX(Inputs!C6*Inputs!C13/Inputs!C8-SUM($D$5:$D59),0),0))) | F60: =D60+E60 | G60: =IFERROR(1/(1+Inputs!C9/Inputs!C8)^56,"") | H60: =F60*G60
B61: 57 | C61: =DATE(YEAR(Inputs!C11),MONTH(Inputs!C11)+(57-1)*(12/Inputs!C8),DAY(Inputs!C11)) | D61: =IF(57<=Inputs!C10*Inputs!C8,Inputs!C6*Inputs!C7/Inputs!C8,0) | E61: =IF(Inputs!C12="Bullet",IF(57=Inputs!C10*Inputs!C8,IF(Inputs!C12="Bullet",Inputs!C6,0),0),IF(Inputs!C12="Full",IF(57<=Inputs!C10*Inputs!C8,Inputs!C6/(Inputs!C10*Inputs!C8),0),IF(57<=Inputs!C10*Inputs!C8,MAX(Inputs!C6*Inputs!C13/Inputs!C8-SUM($D$5:$D60),0),0))) | F61: =D61+E61 | G61: =IFERROR(1/(1+Inputs!C9/Inputs!C8)^57,"") | H61: =F61*G61
B62: 58 | C62: =DATE(YEAR(Inputs!C11),MONTH(Inputs!C11)+(58-1)*(12/Inputs!C8),DAY(Inputs!C11)) | D62: =IF(58<=Inputs!C10*Inputs!C8,Inputs!C6*Inputs!C7/Inputs!C8,0) | E62: =IF(Inputs!C12="Bullet",IF(58=Inputs!C10*Inputs!C8,IF(Inputs!C12="Bullet",Inputs!C6,0),0),IF(Inputs!C12="Full",IF(58<=Inputs!C10*Inputs!C8,Inputs!C6/(Inputs!C10*Inputs!C8),0),IF(58<=Inputs!C10*Inputs!C8,MAX(Inputs!C6*Inputs!C13/Inputs!C8-SUM($D$5:$D61),0),0))) | F62: =D62+E62 | G62: =IFERROR(1/(1+Inputs!C9/Inputs!C8)^58,"") | H62: =F62*G62
B63: 59 | C63: =DATE(YEAR(Inputs!C11),MONTH(Inputs!C11)+(59-1)*(12/Inputs!C8),DAY(Inputs!C11)) | D63: =IF(59<=Inputs!C10*Inputs!C8,Inputs!C6*Inputs!C7/Inputs!C8,0) | E63: =IF(Inputs!C12="Bullet",IF(59=Inputs!C10*Inputs!C8,IF(Inputs!C12="Bullet",Inputs!C6,0),0),IF(Inputs!C12="Full",IF(59<=Inputs!C10*Inputs!C8,Inputs!C6/(Inputs!C10*Inputs!C8),0),IF(59<=Inputs!C10*Inputs!C8,MAX(Inputs!C6*Inputs!C13/Inputs!C8-SUM($D$5:$D62),0),0))) | F63: =D63+E63 | G63: =IFERROR(1/(1+Inputs!C9/Inputs!C8)^59,"") | H63: =F63*G63
B64: 60 | C64: =DATE(YEAR(Inputs!C11),MONTH(Inputs!C11)+(60-1)*(12/Inputs!C8),DAY(Inputs!C11)) | D64: =IF(60<=Inputs!C10*Inputs!C8,Inputs!C6*Inputs!C7/Inputs!C8,0) | E64: =IF(Inputs!C12="Bullet",IF(60=Inputs!C10*Inputs!C8,IF(Inputs!C12="Bullet",Inputs!C6,0),0),IF(Inputs!C12="Full",IF(60<=Inputs!C10*Inputs!C8,Inputs!C6/(Inputs!C10*Inputs!C8),0),IF(60<=Inputs!C10*Inputs!C8,MAX(Inputs!C6*Inputs!C13/Inputs!C8-SUM($D$5:$D63),0),0))) | F64: =D64+E64 | G64: =IFERROR(1/(1+Inputs!C9/Inputs!C8)^60,"") | H64: =F64*G64
B65: 61 | C65: =DATE(YEAR(Inputs!C11),MONTH(Inputs!C11)+(61-1)*(12/Inputs!C8),DAY(Inputs!C11)) | D65: =IF(61<=Inputs!C10*Inputs!C8,Inputs!C6*Inputs!C7/Inputs!C8,0) | E65: =IF(Inputs!C12="Bullet",IF(61=Inputs!C10*Inputs!C8,IF(Inputs!C12="Bullet",Inputs!C6,0),0),IF(Inputs!C12="Full",IF(61<=Inputs!C10*Inputs!C8,Inputs!C6/(Inputs!C10*Inputs!C8),0),IF(61<=Inputs!C10*Inputs!C8,MAX(Inputs!C6*Inputs!C13/Inputs!C8-SUM($D$5:$D64),0),0))) | F65: =D65+E65 | G65: =IFERROR(1/(1+Inputs!C9/Inputs!C8)^61,"") | H65: =F65*G65
B66: 62 | C66: =DATE(YEAR(Inputs!C11),MONTH(Inputs!C11)+(62-1)*(12/Inputs!C8),DAY(Inputs!C11)) | D66: =IF(62<=Inputs!C10*Inputs!C8,Inputs!C6*Inputs!C7/Inputs!C8,0) | E66: =IF(Inputs!C12="Bullet",IF(62=Inputs!C10*Inputs!C8,IF(Inputs!C12="Bullet",Inputs!C6,0),0),IF(Inputs!C12="Full",IF(62<=Inputs!C10*Inputs!C8,Inputs!C6/(Inputs!C10*Inputs!C8),0),IF(62<=Inputs!C10*Inputs!C8,MAX(Inputs!C6*Inputs!C13/Inputs!C8-SUM($D$5:$D65),0),0))) | F66: =D66+E66 | G66: =IFERROR(1/(1+Inputs!C9/Inputs!C8)^62,"") | H66: =F66*G66
B67: 63 | C67: =DATE(YEAR(Inputs!C11),MONTH(Inputs!C11)+(63-1)*(12/Inputs!C8),DAY(Inputs!C11)) | D67: =IF(63<=Inputs!C10*Inputs!C8,Inputs!C6*Inputs!C7/Inputs!C8,0) | E67: =IF(Inputs!C12="Bullet",IF(63=Inputs!C10*Inputs!C8,IF(Inputs!C12="Bullet",Inputs!C6,0),0),IF(Inputs!C12="Full",IF(63<=Inputs!C10*Inputs!C8,Inputs!C6/(Inputs!C10*Inputs!C8),0),IF(63<=Inputs!C10*Inputs!C8,MAX(Inputs!C6*Inputs!C13/Inputs!C8-SUM($D$5:$D66),0),0))) | F67: =D67+E67 | G67: =IFERROR(1/(1+Inputs!C9/Inputs!C8)^63,"") | H67: =F67*G67
B68: 64 | C68: =DATE(YEAR(Inputs!C11),MONTH(Inputs!C11)+(64-1)*(12/Inputs!C8),DAY(Inputs!C11)) | D68: =IF(64<=Inputs!C10*Inputs!C8,Inputs!C6*Inputs!C7/Inputs!C8,0) | E68: =IF(Inputs!C12="Bullet",IF(64=Inputs!C10*Inputs!C8,IF(Inputs!C12="Bullet",Inputs!C6,0),0),IF(Inputs!C12="Full",IF(64<=Inputs!C10*Inputs!C8,Inputs!C6/(Inputs!C10*Inputs!C8),0),IF(64<=Inputs!C10*Inputs!C8,MAX(Inputs!C6*Inputs!C13/Inputs!C8-SUM($D$5:$D67),0),0))) | F68: =D68+E68 | G68: =IFERROR(1/(1+Inputs!C9/Inputs!C8)^64,"") | H68: =F68*G68
B69: 65 | C69: =DATE(YEAR(Inputs!C11),MONTH(Inputs!C11)+(65-1)*(12/Inputs!C8),DAY(Inputs!C11)) | D69: =IF(65<=Inputs!C10*Inputs!C8,Inputs!C6*Inputs!C7/Inputs!C8,0) | E69: =IF(Inputs!C12="Bullet",IF(65=Inputs!C10*Inputs!C8,IF(Inputs!C12="Bullet",Inputs!C6,0),0),IF(Inputs!C12="Full",IF(65<=Inputs!C10*Inputs!C8,Inputs!C6/(Inputs!C10*Inputs!C8),0),IF(65<=Inputs!C10*Inputs!C8,MAX(Inputs!C6*Inputs!C13/Inputs!C8-SUM($D$5:$D68),0),0))) | F69: =D69+E69 | G69: =IFERROR(1/(1+Inputs!C9/Inputs!C8)^65,"") | H69: =F69*G69
B70: 66 | C70: =DATE(YEAR(Inputs!C11),MONTH(Inputs!C11)+(66-1)*(12/Inputs!C8),DAY(Inputs!C11)) | D70: =IF(66<=Inputs!C10*Inputs!C8,Inputs!C6*Inputs!C7/Inputs!C8,0) | E70: =IF(Inputs!C12="Bullet",IF(66=Inputs!C10*Inputs!C8,IF(Inputs!C12="Bullet",Inputs!C6,0),0),IF(Inputs!C12="Full",IF(66<=Inputs!C10*Inputs!C8,Inputs!C6/(Inputs!C10*Inputs!C8),0),IF(66<=Inputs!C10*Inputs!C8,MAX(Inputs!C6*Inputs!C13/Inputs!C8-SUM($D$5:$D69),0),0))) | F70: =D70+E70 | G70: =IFERROR(1/(1+Inputs!C9/Inputs!C8)^66,"") | H70: =F70*G70
B71: 67 | C71: =DATE(YEAR(Inputs!C11),MONTH(Inputs!C11)+(67-1)*(12/Inputs!C8),DAY(Inputs!C11)) | D71: =IF(67<=Inputs!C10*Inputs!C8,Inputs!C6*Inputs!C7/Inputs!C8,0) | E71: =IF(Inputs!C12="Bullet",IF(67=Inputs!C10*Inputs!C8,IF(Inputs!C12="Bullet",Inputs!C6,0),0),IF(Inputs!C12="Full",IF(67<=Inputs!C10*Inputs!C8,Inputs!C6/(Inputs!C10*Inputs!C8),0),IF(67<=Inputs!C10*Inputs!C8,MAX(Inputs!C6*Inputs!C13/Inputs!C8-SUM($D$5:$D70),0),0))) | F71: =D71+E71 | G71: =IFERROR(1/(1+Inputs!C9/Inputs!C8)^67,"") | H71: =F71*G71
B72: 68 | C72: =DATE(YEAR(Inputs!C11),MONTH(Inputs!C11)+(68-1)*(12/Inputs!C8),DAY(Inputs!C11)) | D72: =IF(68<=Inputs!C10*Inputs!C8,Inputs!C6*Inputs!C7/Inputs!C8,0) | E72: =IF(Inputs!C12="Bullet",IF(68=Inputs!C10*Inputs!C8,IF(Inputs!C12="Bullet",Inputs!C6,0),0),IF(Inputs!C12="Full",IF(68<=Inputs!C10*Inputs!C8,Inputs!C6/(Inputs!C10*Inputs!C8),0),IF(68<=Inputs!C10*Inputs!C8,MAX(Inputs!C6*Inputs!C13/Inputs!C8-SUM($D$5:$D71),0),0))) | F72: =D72+E72 | G72: =IFERROR(1/(1+Inputs!C9/Inputs!C8)^68,"") | H72: =F72*G72
B73: 69 | C73: =DATE(YEAR(Inputs!C11),MONTH(Inputs!C11)+(69-1)*(12/Inputs!C8),DAY(Inputs!C11)) | D73: =IF(69<=Inputs!C10*Inputs!C8,Inputs!C6*Inputs!C7/Inputs!C8,0) | E73: =IF(Inputs!C12="Bullet",IF(69=Inputs!C10*Inputs!C8,IF(Inputs!C12="Bullet",Inputs!C6,0),0),IF(Inputs!C12="Full",IF(69<=Inputs!C10*Inputs!C8,Inputs!C6/(Inputs!C10*Inputs!C8),0),IF(69<=Inputs!C10*Inputs!C8,MAX(Inputs!C6*Inputs!C13/Inputs!C8-SUM($D$5:$D72),0),0))) | F73: =D73+E73 | G73: =IFERROR(1/(1+Inputs!C9/Inputs!C8)^69,"") | H73: =F73*G73
B74: 70 | C74: =DATE(YEAR(Inputs!C11),MONTH(Inputs!C11)+(70-1)*(12/Inputs!C8),DAY(Inputs!C11)) | D74: =IF(70<=Inputs!C10*Inputs!C8,Inputs!C6*Inputs!C7/Inputs!C8,0) | E74: =IF(Inputs!C12="Bullet",IF(70=Inputs!C10*Inputs!C8,IF(Inputs!C12="Bullet",Inputs!C6,0),0),IF(Inputs!C12="Full",IF(70<=Inputs!C10*Inputs!C8,Inputs!C6/(Inputs!C10*Inputs!C8),0),IF(70<=Inputs!C10*Inputs!C8,MAX(Inputs!C6*Inputs!C13/Inputs!C8-SUM($D$5:$D73),0),0))) | F74: =D74+E74 | G74: =IFERROR(1/(1+Inputs!C9/Inputs!C8)^70,"") | H74: =F74*G74
B75: 71 | C75: =DATE(YEAR(Inputs!C11),MONTH(Inputs!C11)+(71-1)*(12/Inputs!C8),DAY(Inputs!C11)) | D75: =IF(71<=Inputs!C10*Inputs!C8,Inputs!C6*Inputs!C7/Inputs!C8,0) | E75: =IF(Inputs!C12="Bullet",IF(71=Inputs!C10*Inputs!C8,IF(Inputs!C12="Bullet",Inputs!C6,0),0),IF(Inputs!C12="Full",IF(71<=Inputs!C10*Inputs!C8,Inputs!C6/(Inputs!C10*Inputs!C8),0),IF(71<=Inputs!C10*Inputs!C8,MAX(Inputs!C6*Inputs!C13/Inputs!C8-SUM($D$5:$D74),0),0))) | F75: =D75+E75 | G75: =IFERROR(1/(1+Inputs!C9/Inputs!C8)^71,"") | H75: =F75*G75
B76: 72 | C76: =DATE(YEAR(Inputs!C11),MONTH(Inputs!C11)+(72-1)*(12/Inputs!C8),DAY(Inputs!C11)) | D76: =IF(72<=Inputs!C10*Inputs!C8,Inputs!C6*Inputs!C7/Inputs!C8,0) | E76: =IF(Inputs!C12="Bullet",IF(72=Inputs!C10*Inputs!C8,IF(Inputs!C12="Bullet",Inputs!C6,0),0),IF(Inputs!C12="Full",IF(72<=Inputs!C10*Inputs!C8,Inputs!C6/(Inputs!C10*Inputs!C8),0),IF(72<=Inputs!C10*Inputs!C8,MAX(Inputs!C6*Inputs!C13/Inputs!C8-SUM($D$5:$D75),0),0))) | F76: =D76+E76 | G76: =IFERROR(1/(1+Inputs!C9/Inputs!C8)^72,"") | H76: =F76*G76
B77: 73 | C77: =DATE(YEAR(Inputs!C11),MONTH(Inputs!C11)+(73-1)*(12/Inputs!C8),DAY(Inputs!C11)) | D77: =IF(73<=Inputs!C10*Inputs!C8,Inputs!C6*Inputs!C7/Inputs!C8,0) | E77: =IF(Inputs!C12="Bullet",IF(73=Inputs!C10*Inputs!C8,IF(Inputs!C12="Bullet",Inputs!C6,0),0),IF(Inputs!C12="Full",IF(73<=Inputs!C10*Inputs!C8,Inputs!C6/(Inputs!C10*Inputs!C8),0),IF(73<=Inputs!C10*Inputs!C8,MAX(Inputs!C6*Inputs!C13/Inputs!C8-SUM($D$5:$D76),0),0))) | F77: =D77+E77 | G77: =IFERROR(1/(1+Inputs!C9/Inputs!C8)^73,"") | H77: =F77*G77
B78: 74 | C78: =DATE(YEAR(Inputs!C11),MONTH(Inputs!C11)+(74-1)*(12/Inputs!C8),DAY(Inputs!C11)) | D78: =IF(74<=Inputs!C10*Inputs!C8,Inputs!C6*Inputs!C7/Inputs!C8,0) | E78: =IF(Inputs!C12="Bullet",IF(74=Inputs!C10*Inputs!C8,IF(Inputs!C12="Bullet",Inputs!C6,0),0),IF(Inputs!C12="Full",IF(74<=Inputs!C10*Inputs!C8,Inputs!C6/(Inputs!C10*Inputs!C8),0),IF(74<=Inputs!C10*Inputs!C8,MAX(Inputs!C6*Inputs!C13/Inputs!C8-SUM($D$5:$D77),0),0))) | F78: =D78+E78 | G78: =IFERROR(1/(1+Inputs!C9/Inputs!C8)^74,"") | H78: =F78*G78
B79: 75 | C79: =DATE(YEAR(Inputs!C11),MONTH(Inputs!C11)+(75-1)*(12/Inputs!C8),DAY(Inputs!C11)) | D79: =IF(75<=Inputs!C10*Inputs!C8,Inputs!C6*Inputs!C7/Inputs!C8,0) | E79: =IF(Inputs!C12="Bullet",IF(75=Inputs!C10*Inputs!C8,IF(Inputs!C12="Bullet",Inputs!C6,0),0),IF(Inputs!C12="Full",IF(75<=Inputs!C10*Inputs!C8,Inputs!C6/(Inputs!C10*Inputs!C8),0),IF(75<=Inputs!C10*Inputs!C8,MAX(Inputs!C6*Inputs!C13/Inputs!C8-SUM($D$5:$D78),0),0))) | F79: =D79+E79 | G79: =IFERROR(1/(1+Inputs!C9/Inputs!C8)^75,"") | H79: =F79*G79
B80: 76 | C80: =DATE(YEAR(Inputs!C11),MONTH(Inputs!C11)+(76-1)*(12/Inputs!C8),DAY(Inputs!C11)) | D80: =IF(76<=Inputs!C10*Inputs!C8,Inputs!C6*Inputs!C7/Inputs!C8,0) | E80: =IF(Inputs!C12="Bullet",IF(76=Inputs!C10*Inputs!C8,IF(Inputs!C12="Bullet",Inputs!C6,0),0),IF(Inputs!C12="Full",IF(76<=Inputs!C10*Inputs!C8,Inputs!C6/(Inputs!C10*Inputs!C8),0),IF(76<=Inputs!C10*Inputs!C8,MAX(Inputs!C6*Inputs!C13/Inputs!C8-SUM($D$5:$D79),0),0))) | F80: =D80+E80 | G80: =IFERROR(1/(1+Inputs!C9/Inputs!C8)^76,"") | H80: =F80*G80
B81: 77 | C81: =DATE(YEAR(Inputs!C11),MONTH(Inputs!C11)+(77-1)*(12/Inputs!C8),DAY(Inputs!C11)) | D81: =IF(77<=Inputs!C10*Inputs!C8,Inputs!C6*Inputs!C7/Inputs!C8,0) | E81: =IF(Inputs!C12="Bullet",IF(77=Inputs!C10*Inputs!C8,IF(Inputs!C12="Bullet",Inputs!C6,0),0),IF(Inputs!C12="Full",IF(77<=Inputs!C10*Inputs!C8,Inputs!C6/(Inputs!C10*Inputs!C8),0),IF(77<=Inputs!C10*Inputs!C8,MAX(Inputs!C6*Inputs!C13/Inputs!C8-SUM($D$5:$D80),0),0))) | F81: =D81+E81 | G81: =IFERROR(1/(1+Inputs!C9/Inputs!C8)^77,"") | H81: =F81*G81
B82: 78 | C82: =DATE(YEAR(Inputs!C11),MONTH(Inputs!C11)+(78-1)*(12/Inputs!C8),DAY(Inputs!C11)) | D82: =IF(78<=Inputs!C10*Inputs!C8,Inputs!C6*Inputs!C7/Inputs!C8,0) | E82: =IF(Inputs!C12="Bullet",IF(78=Inputs!C10*Inputs!C8,IF(Inputs!C12="Bullet",Inputs!C6,0),0),IF(Inputs!C12="Full",IF(78<=Inputs!C10*Inputs!C8,Inputs!C6/(Inputs!C10*Inputs!C8),0),IF(78<=Inputs!C10*Inputs!C8,MAX(Inputs!C6*Inputs!C13/Inputs!C8-SUM($D$5:$D81),0),0))) | F82: =D82+E82 | G82: =IFERROR(1/(1+Inputs!C9/Inputs!C8)^78,"") | H82: =F82*G82
B83: 79 | C83: =DATE(YEAR(Inputs!C11),MONTH(Inputs!C11)+(79-1)*(12/Inputs!C8),DAY(Inputs!C11)) | D83: =IF(79<=Inputs!C10*Inputs!C8,Inputs!C6*Inputs!C7/Inputs!C8,0) | E83: =IF(Inputs!C12="Bullet",IF(79=Inputs!C10*Inputs!C8,IF(Inputs!C12="Bullet",Inputs!C6,0),0),IF(Inputs!C12="Full",IF(79<=Inputs!C10*Inputs!C8,Inputs!C6/(Inputs!C10*Inputs!C8),0),IF(79<=Inputs!C10*Inputs!C8,MAX(Inputs!C6*Inputs!C13/Inputs!C8-SUM($D$5:$D82),0),0))) | F83: =D83+E83 | G83: =IFERROR(1/(1+Inputs!C9/Inputs!C8)^79,"") | H83: =F83*G83
B84: 80 | C84: =DATE(YEAR(Inputs!C11),MONTH(Inputs!C11)+(80-1)*(12/Inputs!C8),DAY(Inputs!C11)) | D84: =IF(80<=Inputs!C10*Inputs!C8,Inputs!C6*Inputs!C7/Inputs!C8,0) | E84: =IF(Inputs!C12="Bullet",IF(80=Inputs!C10*Inputs!C8,IF(Inputs!C12="Bullet",Inputs!C6,0),0),IF(Inputs!C12="Full",IF(80<=Inputs!C10*Inputs!C8,Inputs!C6/(Inputs!C10*Inputs!C8),0),IF(80<=Inputs!C10*Inputs!C8,MAX(Inputs!C6*Inputs!C13/Inputs!C8-SUM($D$5:$D83),0),0))) | F84: =D84+E84 | G84: =IFERROR(1/(1+Inputs!C9/Inputs!C8)^80,"") | H84: =F84*G84
B85: 81 | C85: =DATE(YEAR(Inputs!C11),MONTH(Inputs!C11)+(81-1)*(12/Inputs!C8),DAY(Inputs!C11)) | D85: =IF(81<=Inputs!C10*Inputs!C8,Inputs!C6*Inputs!C7/Inputs!C8,0) | E85: =IF(Inputs!C12="Bullet",IF(81=Inputs!C10*Inputs!C8,IF(Inputs!C12="Bullet",Inputs!C6,0),0),IF(Inputs!C12="Full",IF(81<=Inputs!C10*Inputs!C8,Inputs!C6/(Inputs!C10*Inputs!C8),0),IF(81<=Inputs!C10*Inputs!C8,MAX(Inputs!C6*Inputs!C13/Inputs!C8-SUM($D$5:$D84),0),0))) | F85: =D85+E85 | G85: =IFERROR(1/(1+Inputs!C9/Inputs!C8)^81,"") | H85: =F85*G85
B86: 82 | C86: =DATE(YEAR(Inputs!C11),MONTH(Inputs!C11)+(82-1)*(12/Inputs!C8),DAY(Inputs!C11)) | D86: =IF(82<=Inputs!C10*Inputs!C8,Inputs!C6*Inputs!C7/Inputs!C8,0) | E86: =IF(Inputs!C12="Bullet",IF(82=Inputs!C10*Inputs!C8,IF(Inputs!C12="Bullet",Inputs!C6,0),0),IF(Inputs!C12="Full",IF(82<=Inputs!C10*Inputs!C8,Inputs!C6/(Inputs!C10*Inputs!C8),0),IF(82<=Inputs!C10*Inputs!C8,MAX(Inputs!C6*Inputs!C13/Inputs!C8-SUM($D$5:$D85),0),0))) | F86: =D86+E86 | G86: =IFERROR(1/(1+Inputs!C9/Inputs!C8)^82,"") | H86: =F86*G86
B87: 83 | C87: =DATE(YEAR(Inputs!C11),MONTH(Inputs!C11)+(83-1)*(12/Inputs!C8),DAY(Inputs!C11)) | D87: =IF(83<=Inputs!C10*Inputs!C8,Inputs!C6*Inputs!C7/Inputs!C8,0) | E87: =IF(Inputs!C12="Bullet",IF(83=Inputs!C10*Inputs!C8,IF(Inputs!C12="Bullet",Inputs!C6,0),0),IF(Inputs!C12="Full",IF(83<=Inputs!C10*Inputs!C8,Inputs!C6/(Inputs!C10*Inputs!C8),0),IF(83<=Inputs!C10*Inputs!C8,MAX(Inputs!C6*Inputs!C13/Inputs!C8-SUM($D$5:$D86),0),0))) | F87: =D87+E87 | G87: =IFERROR(1/(1+Inputs!C9/Inputs!C8)^83,"") | H87: =F87*G87
B88: 84 | C88: =DATE(YEAR(Inputs!C11),MONTH(Inputs!C11)+(84-1)*(12/Inputs!C8),DAY(Inputs!C11)) | D88: =IF(84<=Inputs!C10*Inputs!C8,Inputs!C6*Inputs!C7/Inputs!C8,0) | E88: =IF(Inputs!C12="Bullet",IF(84=Inputs!C10*Inputs!C8,IF(Inputs!C12="Bullet",Inputs!C6,0),0),IF(Inputs!C12="Full",IF(84<=Inputs!C10*Inputs!C8,Inputs!C6/(Inputs!C10*Inputs!C8),0),IF(84<=Inputs!C10*Inputs!C8,MAX(Inputs!C6*Inputs!C13/Inputs!C8-SUM($D$5:$D87),0),0))) | F88: =D88+E88 | G88: =IFERROR(1/(1+Inputs!C9/Inputs!C8)^84,"") | H88: =F88*G88
B89: 85 | C89: =DATE(YEAR(Inputs!C11),MONTH(Inputs!C11)+(85-1)*(12/Inputs!C8),DAY(Inputs!C11)) | D89: =IF(85<=Inputs!C10*Inputs!C8,Inputs!C6*Inputs!C7/Inputs!C8,0) | E89: =IF(Inputs!C12="Bullet",IF(85=Inputs!C10*Inputs!C8,IF(Inputs!C12="Bullet",Inputs!C6,0),0),IF(Inputs!C12="Full",IF(85<=Inputs!C10*Inputs!C8,Inputs!C6/(Inputs!C10*Inputs!C8),0),IF(85<=Inputs!C10*Inputs!C8,MAX(Inputs!C6*Inputs!C13/Inputs!C8-SUM($D$5:$D88),0),0))) | F89: =D89+E89 | G89: =IFERROR(1/(1+Inputs!C9/Inputs!C8)^85,"") | H89: =F89*G89
B90: 86 | C90: =DATE(YEAR(Inputs!C11),MONTH(Inputs!C11)+(86-1)*(12/Inputs!C8),DAY(Inputs!C11)) | D90: =IF(86<=Inputs!C10*Inputs!C8,Inputs!C6*Inputs!C7/Inputs!C8,0) | E90: =IF(Inputs!C12="Bullet",IF(86=Inputs!C10*Inputs!C8,IF(Inputs!C12="Bullet",Inputs!C6,0),0),IF(Inputs!C12="Full",IF(86<=Inputs!C10*Inputs!C8,Inputs!C6/(Inputs!C10*Inputs!C8),0),IF(86<=Inputs!C10*Inputs!C8,MAX(Inputs!C6*Inputs!C13/Inputs!C8-SUM($D$5:$D89),0),0))) | F90: =D90+E90 | G90: =IFERROR(1/(1+Inputs!C9/Inputs!C8)^86,"") | H90: =F90*G90
B91: 87 | C91: =DATE(YEAR(Inputs!C11),MONTH(Inputs!C11)+(87-1)*(12/Inputs!C8),DAY(Inputs!C11)) | D91: =IF(87<=Inputs!C10*Inputs!C8,Inputs!C6*Inputs!C7/Inputs!C8,0) | E91: =IF(Inputs!C12="Bullet",IF(87=Inputs!C10*Inputs!C8,IF(Inputs!C12="Bullet",Inputs!C6,0),0),IF(Inputs!C12="Full",IF(87<=Inputs!C10*Inputs!C8,Inputs!C6/(Inputs!C10*Inputs!C8),0),IF(87<=Inputs!C10*Inputs!C8,MAX(Inputs!C6*Inputs!C13/Inputs!C8-SUM($D$5:$D90),0),0))) | F91: =D91+E91 | G91: =IFERROR(1/(1+Inputs!C9/Inputs!C8)^87,"") | H91: =F91*G91
B92: 88 | C92: =DATE(YEAR(Inputs!C11),MONTH(Inputs!C11)+(88-1)*(12/Inputs!C8),DAY(Inputs!C11)) | D92: =IF(88<=Inputs!C10*Inputs!C8,Inputs!C6*Inputs!C7/Inputs!C8,0) | E92: =IF(Inputs!C12="Bullet",IF(88=Inputs!C10*Inputs!C8,IF(Inputs!C12="Bullet",Inputs!C6,0),0),IF(Inputs!C12="Full",IF(88<=Inputs!C10*Inputs!C8,Inputs!C6/(Inputs!C10*Inputs!C8),0),IF(88<=Inputs!C10*Inputs!C8,MAX(Inputs!C6*Inputs!C13/Inputs!C8-SUM($D$5:$D91),0),0))) | F92: =D92+E92 | G92: =IFERROR(1/(1+Inputs!C9/Inputs!C8)^88,"") | H92: =F92*G92
B93: 89 | C93: =DATE(YEAR(Inputs!C11),MONTH(Inputs!C11)+(89-1)*(12/Inputs!C8),DAY(Inputs!C11)) | D93: =IF(89<=Inputs!C10*Inputs!C8,Inputs!C6*Inputs!C7/Inputs!C8,0) | E93: =IF(Inputs!C12="Bullet",IF(89=Inputs!C10*Inputs!C8,IF(Inputs!C12="Bullet",Inputs!C6,0),0),IF(Inputs!C12="Full",IF(89<=Inputs!C10*Inputs!C8,Inputs!C6/(Inputs!C10*Inputs!C8),0),IF(89<=Inputs!C10*Inputs!C8,MAX(Inputs!C6*Inputs!C13/Inputs!C8-SUM($D$5:$D92),0),0))) | F93: =D93+E93 | G93: =IFERROR(1/(1+Inputs!C9/Inputs!C8)^89,"") | H93: =F93*G93
B94: 90 | C94: =DATE(YEAR(Inputs!C11),MONTH(Inputs!C11)+(90-1)*(12/Inputs!C8),DAY(Inputs!C11)) | D94: =IF(90<=Inputs!C10*Inputs!C8,Inputs!C6*Inputs!C7/Inputs!C8,0) | E94: =IF(Inputs!C12="Bullet",IF(90=Inputs!C10*Inputs!C8,IF(Inputs!C12="Bullet",Inputs!C6,0),0),IF(Inputs!C12="Full",IF(90<=Inputs!C10*Inputs!C8,Inputs!C6/(Inputs!C10*Inputs!C8),0),IF(90<=Inputs!C10*Inputs!C8,MAX(Inputs!C6*Inputs!C13/Inputs!C8-SUM($D$5:$D93),0),0))) | F94: =D94+E94 | G94: =IFERROR(1/(1+Inputs!C9/Inputs!C8)^90,"") | H94: =F94*G94
B95: 91 | C95: =DATE(YEAR(Inputs!C11),MONTH(Inputs!C11)+(91-1)*(12/Inputs!C8),DAY(Inputs!C11)) | D95: =IF(91<=Inputs!C10*Inputs!C8,Inputs!C6*Inputs!C7/Inputs!C8,0) | E95: =IF(Inputs!C12="Bullet",IF(91=Inputs!C10*Inputs!C8,IF(Inputs!C12="Bullet",Inputs!C6,0),0),IF(Inputs!C12="Full",IF(91<=Inputs!C10*Inputs!C8,Inputs!C6/(Inputs!C10*Inputs!C8),0),IF(91<=Inputs!C10*Inputs!C8,MAX(Inputs!C6*Inputs!C13/Inputs!C8-SUM($D$5:$D94),0),0))) | F95: =D95+E95 | G95: =IFERROR(1/(1+Inputs!C9/Inputs!C8)^91,"") | H95: =F95*G95
B96: 92 | C96: =DATE(YEAR(Inputs!C11),MONTH(Inputs!C11)+(92-1)*(12/Inputs!C8),DAY(Inputs!C11)) | D96: =IF(92<=Inputs!C10*Inputs!C8,Inputs!C6*Inputs!C7/Inputs!C8,0) | E96: =IF(Inputs!C12="Bullet",IF(92=Inputs!C10*Inputs!C8,IF(Inputs!C12="Bullet",Inputs!C6,0),0),IF(Inputs!C12="Full",IF(92<=Inputs!C10*Inputs!C8,Inputs!C6/(Inputs!C10*Inputs!C8),0),IF(92<=Inputs!C10*Inputs!C8,MAX(Inputs!C6*Inputs!C13/Inputs!C8-SUM($D$5:$D95),0),0))) | F96: =D96+E96 | G96: =IFERROR(1/(1+Inputs!C9/Inputs!C8)^92,"") | H96: =F96*G96
B97: 93 | C97: =DATE(YEAR(Inputs!C11),MONTH(Inputs!C11)+(93-1)*(12/Inputs!C8),DAY(Inputs!C11)) | D97: =IF(93<=Inputs!C10*Inputs!C8,Inputs!C6*Inputs!C7/Inputs!C8,0) | E97: =IF(Inputs!C12="Bullet",IF(93=Inputs!C10*Inputs!C8,IF(Inputs!C12="Bullet",Inputs!C6,0),0),IF(Inputs!C12="Full",IF(93<=Inputs!C10*Inputs!C8,Inputs!C6/(Inputs!C10*Inputs!C8),0),IF(93<=Inputs!C10*Inputs!C8,MAX(Inputs!C6*Inputs!C13/Inputs!C8-SUM($D$5:$D96),0),0))) | F97: =D97+E97 | G97: =IFERROR(1/(1+Inputs!C9/Inputs!C8)^93,"") | H97: =F97*G97
B98: 94 | C98: =DATE(YEAR(Inputs!C11),MONTH(Inputs!C11)+(94-1)*(12/Inputs!C8),DAY(Inputs!C11)) | D98: =IF(94<=Inputs!C10*Inputs!C8,Inputs!C6*Inputs!C7/Inputs!C8,0) | E98: =IF(Inputs!C12="Bullet",IF(94=Inputs!C10*Inputs!C8,IF(Inputs!C12="Bullet",Inputs!C6,0),0),IF(Inputs!C12="Full",IF(94<=Inputs!C10*Inputs!C8,Inputs!C6/(Inputs!C10*Inputs!C8),0),IF(94<=Inputs!C10*Inputs!C8,MAX(Inputs!C6*Inputs!C13/Inputs!C8-SUM($D$5:$D97),0),0))) | F98: =D98+E98 | G98: =IFERROR(1/(1+Inputs!C9/Inputs!C8)^94,"") | H98: =F98*G98
B99: 95 | C99: =DATE(YEAR(Inputs!C11),MONTH(Inputs!C11)+(95-1)*(12/Inputs!C8),DAY(Inputs!C11)) | D99: =IF(95<=Inputs!C10*Inputs!C8,Inputs!C6*Inputs!C7/Inputs!C8,0) | E99: =IF(Inputs!C12="Bullet",IF(95=Inputs!C10*Inputs!C8,IF(Inputs!C12="Bullet",Inputs!C6,0),0),IF(Inputs!C12="Full",IF(95<=Inputs!C10*Inputs!C8,Inputs!C6/(Inputs!C10*Inputs!C8),0),IF(95<=Inputs!C10*Inputs!C8,MAX(Inputs!C6*Inputs!C13/Inputs!C8-SUM($D$5:$D98),0),0))) | F99: =D99+E99 | G99: =IFERROR(1/(1+Inputs!C9/Inputs!C8)^95,"") | H99: =F99*G99
B100: 96 | C100: =DATE(YEAR(Inputs!C11),MONTH(Inputs!C11)+(96-1)*(12/Inputs!C8),DAY(Inputs!C11)) | D100: =IF(96<=Inputs!C10*Inputs!C8,Inputs!C6*Inputs!C7/Inputs!C8,0) | E100: =IF(Inputs!C12="Bullet",IF(96=Inputs!C10*Inputs!C8,IF(Inputs!C12="Bullet",Inputs!C6,0),0),IF(Inputs!C12="Full",IF(96<=Inputs!C10*Inputs!C8,Inputs!C6/(Inputs!C10*Inputs!C8),0),IF(96<=Inputs!C10*Inputs!C8,MAX(Inputs!C6*Inputs!C13/Inputs!C8-SUM($D$5:$D99),0),0))) | F100: =D100+E100 | G100: =IFERROR(1/(1+Inputs!C9/Inputs!C8)^96,"") | H100: =F100*G100
...

Sheet Results
B1: DURATION & RISK METRICS — LIVE OUTPUTS
B2: All values update automatically when Inputs are changed
B4: METRIC | C4: VALUE | D4: FORMULA / NOTES
B6: Number of Periods | C6: =Inputs!C10*Inputs!C8 | D6: Tenor × Frequency
B7: Periodic Coupon Amount (₹ Cr) | C7: =Inputs!C6*Inputs!C7/Inputs!C8 | D7: Principal × Coupon Rate / Frequency
B8: ➤ Macaulay Duration (Years) | C8: ='Cash Flows'!I126 | D8: Weighted avg time to receive cash flows
B9: Modified Duration (Years) | C9: =C8/(1+Inputs!C9/Inputs!C8) | D9: Macaulay / (1 + y/f) — price sensitivity to yield
B10: DV01 — ₹ Cr per basis point | C10: =(C9*Inputs!C6)/10000 | D10: Price change per 1bp yield increase
B11: Convexity | C11: =((1+Inputs!C9/Inputs!C8)^2*C9/(Inputs!C9/Inputs!C8)^2)-((1+Inputs!C9/Inputs!C8)*Inputs!C9/Inputs!C8+1)/((Inputs!C9/Inputs!C8)^2*(1+Inputs!C9/Inputs!C8)) | D11: Second-order price sensitivity — for small yield changes
B12: Price per ₹100 Face (₹) | C12: =SUMPRODUCT((1/(1+Inputs!C9/Inputs!C8)^ROW(INDIRECT("1:"&Inputs!C8*Inputs!C10)))*(IF(ROW(INDIRECT("1:"&Inputs!C8*Inputs!C10))<Inputs!C8*Inputs!C10,Inputs!C6*Inputs!C7/Inputs!C8,Inputs!C6*Inputs!C7/Inputs!C8+Inputs!C6)))/(Inputs!C6*100)) | D12: Issue price / market price per ₹100 face value
B13: Modified Duration × Face Value (₹ Cr) | C13: =C9*Inputs!C6 | D13: Duration × Notional — for hedging
B14: Price Change per +100bp (₹ Cr) | C14: =-C9*Inputs!C6*0.01+C12*0.5*C11*0.0001 | D14: Approx price drop for 100bp yield rise (includes convexity)
B15: Price Change per -100bp (₹ Cr) | C15: =C9*Inputs!C6*0.01+C12*0.5*C11*0.0001 | D15: Approx price rise for 100bp yield fall (includes convexity)
B16: Annualised Cost (if borrowing — all-in %) | C16: =Inputs!C7+((100-C12)/C8) | D16: Approx all-in cost if issued at discount/premium
B18: KEY ASSUMPTIONS
B20: ✓ Flat yield curve — same yield used for all periods
B21: ✓ Coupon dates equally spaced at 1/f years
B22: ✓ No call/put options embedded (plain vanilla loan)
B23: ✓ Day count: 30/360 (change in CF sheet if ACT/ACT needed)
B24: ✓ Convexity formula: simplified approximation (Taylor series)
B26: 🔑 Green = Key duration metrics | Yellow = Derived / price metrics | Red = Downside sensitivity

Sheet What-If
B1: YIELD vs DURATION — SENSITIVITY TABLE
B2: Rows = Yield scenarios (YTM) | Columns = Tenor scenarios (Years) | Values = Modified Duration in Years
B4: Yield \ Tenor → | C4: 1Y | D4: 2Y | E4: 3Y | F4: 4Y | G4: 5Y | H4: 6Y | I4: 7Y | J4: 8Y | K4: 9Y | L4: 10Y | M4: 11Y | N4: 12Y | O4: 13Y | P4: 14Y | Q4: 15Y
B5: 5.00% | C5: =IFERROR(1/(1+5.0/100),0) | D5: =IFERROR(2/(1+5.0/100),0) | E5: =IFERROR(3/(1+5.0/100),0) | F5: =IFERROR(4/(1+5.0/100),0) | G5: =IFERROR(5/(1+5.0/100),0) | H5: =IFERROR(6/(1+5.0/100),0) | I5: =IFERROR(7/(1+5.0/100),0) | J5: =IFERROR(8/(1+5.0/100),0) | K5: =IFERROR(9/(1+5.0/100),0) | L5: =IFERROR(10/(1+5.0/100),0) | M5: =IFERROR(11/(1+5.0/100),0) | N5: =IFERROR(12/(1+5.0/100),0) | O5: =IFERROR(13/(1+5.0/100),0) | P5: =IFERROR(14/(1+5.0/100),0) | Q5: =IFERROR(15/(1+5.0/100),0)
B6: 5.25% | C6: =IFERROR(1/(1+5.25/100),0) | D6: =IFERROR(2/(1+5.25/100),0) | E6: =IFERROR(3/(1+5.25/100),0) | F6: =IFERROR(4/(1+5.25/100),0) | G6: =IFERROR(5/(1+5.25/100),0) | H6: =IFERROR(6/(1+5.25/100),0) | I6: =IFERROR(7/(1+5.25/100),0) | J6: =IFERROR(8/(1+5.25/100),0) | K6: =IFERROR(9/(1+5.25/100),0) | L6: =IFERROR(10/(1+5.25/100),0) | M6: =IFERROR(11/(1+5.25/100),0) | N6: =IFERROR(12/(1+5.25/100),0) | O6: =IFERROR(13/(1+5.25/100),0) | P6: =IFERROR(14/(1+5.25/100),0) | Q6: =IFERROR(15/(1+5.25/100),0)
B7: 5.50% | C7: =IFERROR(1/(1+5.5/100),0) | D7: =IFERROR(2/(1+5.5/100),0) | E7: =IFERROR(3/(1+5.5/100),0) | F7: =IFERROR(4/(1+5.5/100),0) | G7: =IFERROR(5/(1+5.5/100),0) | H7: =IFERROR(6/(1+5.5/100),0) | I7: =IFERROR(7/(1+5.5/100),0) | J7: =IFERROR(8/(1+5.5/100),0) | K7: =IFERROR(9/(1+5.5/100),0) | L7: =IFERROR(10/(1+5.5/100),0) | M7: =IFERROR(11/(1+5.5/100),0) | N7: =IFERROR(12/(1+5.5/100),0) | O7: =IFERROR(13/(1+5.5/100),0) | P7: =IFERROR(14/(1+5.5/100),0) | Q7: =IFERROR(15/(1+5.5/100),0)
B8: 5.75% | C8: =IFERROR(1/(1+5.75/100),0) | D8: =IFERROR(2/(1+5.75/100),0) | E8: =IFERROR(3/(1+5.75/100),0) | F8: =IFERROR(4/(1+5.75/100),0) | G8: =IFERROR(5/(1+5.75/100),0) | H8: =IFERROR(6/(1+5.75/100),0) | I8: =IFERROR(7/(1+5.75/100),0) | J8: =IFERROR(8/(1+5.75/100),0) | K8: =IFERROR(9/(1+5.75/100),0) | L8: =IFERROR(10/(1+5.75/100),0) | M8: =IFERROR(11/(1+5.75/100),0) | N8: =IFERROR(12/(1+5.75/100),0) | O8: =IFERROR(13/(1+5.75/100),0) | P8: =IFERROR(14/(1+5.75/100),0) | Q8: =IFERROR(15/(1+5.75/100),0)
B9: 6.00% | C9: =IFERROR(1/(1+6.0/100),0) | D9: =IFERROR(2/(1+6.0/100),0) | E9: =IFERROR(3/(1+6.0/100),0) | F9: =IFERROR(4/(1+6.0/100),0) | G9: =IFERROR(5/(1+6.0/100),0) | H9: =IFERROR(6/(1+6.0/100),0) | I9: =IFERROR(7/(1+6.0/100),0) | J9: =IFERROR(8/(1+6.0/100),0) | K9: =IFERROR(9/(1+6.0/100),0) | L9: =IFERROR(10/(1+6.0/100),0) | M9: =IFERROR(11/(1+6.0/100),0) | N9: =IFERROR(12/(1+6.0/100),0) | O9: =IFERROR(13/(1+6.0/100),0) | P9: =IFERROR(14/(1+6.0/100),0) | Q9: =IFERROR(15/(1+6.0/100),0)
B10: 6.25% | C10: =IFERROR(1/(1+6.25/100),0) | D10: =IFERROR(2/(1+6.25/100),0) | E10: =IFERROR(3/(1+6.25/100),0) | F10: =IFERROR(4/(1+6.25/100),0) | G10: =IFERROR(5/(1+6.25/100),0) | H10: =IFERROR(6/(1+6.25/100),0) | I10: =IFERROR(7/(1+6.25/100),0) | J10: =IFERROR(8/(1+6.25/100),0) | K10: =IFERROR(9/(1+6.25/100),0) | L10: =IFERROR(10/(1+6.25/100),0) | M10: =IFERROR(11/(1+6.25/100),0) | N10: =IFERROR(12/(1+6.25/100),0) | O10: =IFERROR(13/(1+6.25/100),0) | P10: =IFERROR(14/(1+6.25/100),0) | Q10: =IFERROR(15/(1+6.25/100),0)
B11: 6.50% | C11: =IFERROR(1/(1+6.5/100),0) | D11: =IFERROR(2/(1+6.5/100),0) | E11: =IFERROR(3/(1+6.5/100),0) | F11: =IFERROR(4/(1+6.5/100),0) | G11: =IFERROR(5/(1+6.5/100),0) | H11: =IFERROR(6/(1+6.5/100),0) | I11: =IFERROR(7/(1+6.5/100),0) | J11: =IFERROR(8/(1+6.5/100),0) | K11: =IFERROR(9/(1+6.5/100),0) | L11: =IFERROR(10/(1+6.5/100),0) | M11: =IFERROR(11/(1+6.5/100),0) | N11: =IFERROR(12/(1+6.5/100),0) | O11: =IFERROR(13/(1+6.5/100),0) | P11: =IFERROR(14/(1+6.5/100),0) | Q11: =IFERROR(15/(1+6.5/100),0)
B12: 6.75% | C12: =IFERROR(1/(1+6.75/100),0) | D12: =IFERROR(2/(1+6.75/100),0) | E12: =IFERROR(3/(1+6.75/100),0) | F12: =IFERROR(4/(1+6.75/100),0) | G12: =IFERROR(5/(1+6.75/100),0) | H12: =IFERROR(6/(1+6.75/100),0) | I12: =IFERROR(7/(1+6.75/100),0) | J12: =IFERROR(8/(1+6.75/100),0) | K12: =IFERROR(9/(1+6.75/100),0) | L12: =IFERROR(10/(1+6.75/100),0) | M12: =IFERROR(11/(1+6.75/100),0) | N12: =IFERROR(12/(1+6.75/100),0) | O12: =IFERROR(13/(1+6.75/100),0) | P12: =IFERROR(14/(1+6.75/100),0) | Q12: =IFERROR(15/(1+6.75/100),0)
B13: 7.00% | C13: =IFERROR(1/(1+7.0/100),0) | D13: =IFERROR(2/(1+7.0/100),0) | E13: =IFERROR(3/(1+7.0/100),0) | F13: =IFERROR(4/(1+7.0/100),0) | G13: =IFERROR(5/(1+7.0/100),0) | H13: =IFERROR(6/(1+7.0/100),0) | I13: =IFERROR(7/(1+7.0/100),0) | J13: =IFERROR(8/(1+7.0/100),0) | K13: =IFERROR(9/(1+7.0/100),0) | L13: =IFERROR(10/(1+7.0/100),0) | M13: =IFERROR(11/(1+7.0/100),0) | N13: =IFERROR(12/(1+7.0/100),0) | O13: =IFERROR(13/(1+7.0/100),0) | P13: =IFERROR(14/(1+7.0/100),0) | Q13: =IFERROR(15/(1+7.0/100),0)
B14: 7.25% | C14: =IFERROR(1/(1+7.25/100),0) | D14: =IFERROR(2/(1+7.25/100),0) | E14: =IFERROR(3/(1+7.25/100),0) | F14: =IFERROR(4/(1+7.25/100),0) | G14: =IFERROR(5/(1+7.25/100),0) | H14: =IFERROR(6/(1+7.25/100),0) | I14: =IFERROR(7/(1+7.25/100),0) | J14: =IFERROR(8/(1+7.25/100),0) | K14: =IFERROR(9/(1+7.25/100),0) | L14: =IFERROR(10/(1+7.25/100),0) | M14: =IFERROR(11/(1+7.25/100),0) | N14: =IFERROR(12/(1+7.25/100),0) | O14: =IFERROR(13/(1+7.25/100),0) | P14: =IFERROR(14/(1+7.25/100),0) | Q14: =IFERROR(15/(1+7.25/100),0)
B15: 7.50% | C15: =IFERROR(1/(1+7.5/100),0) | D15: =IFERROR(2/(1+7.5/100),0) | E15: =IFERROR(3/(1+7.5/100),0) | F15: =IFERROR(4/(1+7.5/100),0) | G15: =IFERROR(5/(1+7.5/100),0) | H15: =IFERROR(6/(1+7.5/100),0) | I15: =IFERROR(7/(1+7.5/100),0) | J15: =IFERROR(8/(1+7.5/100),0) | K15: =IFERROR(9/(1+7.5/100),0) | L15: =IFERROR(10/(1+7.5/100),0) | M15: =IFERROR(11/(1+7.5/100),0) | N15: =IFERROR(12/(1+7.5/100),0) | O15: =IFERROR(13/(1+7.5/100),0) | P15: =IFERROR(14/(1+7.5/100),0) | Q15: =IFERROR(15/(1+7.5/100),0)
B16: 7.75% | C16: =IFERROR(1/(1+7.75/100),0) | D16: =IFERROR(2/(1+7.75/100),0) | E16: =IFERROR(3/(1+7.75/100),0) | F16: =IFERROR(4/(1+7.75/100),0) | G16: =IFERROR(5/(1+7.75/100),0) | H16: =IFERROR(6/(1+7.75/100),0) | I16: =IFERROR(7/(1+7.75/100),0) | J16: =IFERROR(8/(1+7.75/100),0) | K16: =IFERROR(9/(1+7.75/100),0) | L16: =IFERROR(10/(1+7.75/100),0) | M16: =IFERROR(11/(1+7.75/100),0) | N16: =IFERROR(12/(1+7.75/100),0) | O16: =IFERROR(13/(1+7.75/100),0) | P16: =IFERROR(14/(1+7.75/100),0) | Q16: =IFERROR(15/(1+7.75/100),0)
B17: 8.00% | C17: =IFERROR(1/(1+8.0/100),0) | D17: =IFERROR(2/(1+8.0/100),0) | E17: =IFERROR(3/(1+8.0/100),0) | F17: =IFERROR(4/(1+8.0/100),0) | G17: =IFERROR(5/(1+8.0/100),0) | H17: =IFERROR(6/(1+8.0/100),0) | I17: =IFERROR(7/(1+8.0/100),0) | J17: =IFERROR(8/(1+8.0/100),0) | K17: =IFERROR(9/(1+8.0/100),0) | L17: =IFERROR(10/(1+8.0/100),0) | M17: =IFERROR(11/(1+8.0/100),0) | N17: =IFERROR(12/(1+8.0/100),0) | O17: =IFERROR(13/(1+8.0/100),0) | P17: =IFERROR(14/(1+8.0/100),0) | Q17: =IFERROR(15/(1+8.0/100),0)
B18: 8.25% | C18: =IFERROR(1/(1+8.25/100),0) | D18: =IFERROR(2/(1+8.25/100),0) | E18: =IFERROR(3/(1+8.25/100),0) | F18: =IFERROR(4/(1+8.25/100),0) | G18: =IFERROR(5/(1+8.25/100),0) | H18: =IFERROR(6/(1+8.25/100),0) | I18: =IFERROR(7/(1+8.25/100),0) | J18: =IFERROR(8/(1+8.25/100),0) | K18: =IFERROR(9/(1+8.25/100),0) | L18: =IFERROR(10/(1+8.25/100),0) | M18: =IFERROR(11/(1+8.25/100),0) | N18: =IFERROR(12/(1+8.25/100),0) | O18: =IFERROR(13/(1+8.25/100),0) | P18: =IFERROR(14/(1+8.25/100),0) | Q18: =IFERROR(15/(1+8.25/100),0)
B19: 8.50% | C19: =IFERROR(1/(1+8.5/100),0) | D19: =IFERROR(2/(1+8.5/100),0) | E19: =IFERROR(3/(1+8.5/100),0) | F19: =IFERROR(4/(1+8.5/100),0) | G19: =IFERROR(5/(1+8.5/100),0) | H19: =IFERROR(6/(1+8.5/100),0) | I19: =IFERROR(7/(1+8.5/100),0) | J19: =IFERROR(8/(1+8.5/100),0) | K19: =IFERROR(9/(1+8.5/100),0) | L19: =IFERROR(10/(1+8.5/100),0) | M19: =IFERROR(11/(1+8.5/100),0) | N19: =IFERROR(12/(1+8.5/100),0) | O19: =IFERROR(13/(1+8.5/100),0) | P19: =IFERROR(14/(1+8.5/100),0) | Q19: =IFERROR(15/(1+8.5/100),0)
B20: 8.75% | C20: =IFERROR(1/(1+8.75/100),0) | D20: =IFERROR(2/(1+8.75/100),0) | E20: =IFERROR(3/(1+8.75/100),0) | F20: =IFERROR(4/(1+8.75/100),0) | G20: =IFERROR(5/(1+8.75/100),0) | H20: =IFERROR(6/(1+8.75/100),0) | I20: =IFERROR(7/(1+8.75/100),0) | J20: =IFERROR(8/(1+8.75/100),0) | K20: =IFERROR(9/(1+8.75/100),0) | L20: =IFERROR(10/(1+8.75/100),0) | M20: =IFERROR(11/(1+8.75/100),0) | N20: =IFERROR(12/(1+8.75/100),0) | O20: =IFERROR(13/(1+8.75/100),0) | P20: =IFERROR(14/(1+8.75/100),0) | Q20: =IFERROR(15/(1+8.75/100),0)
B21: 9.00% | C21: =IFERROR(1/(1+9.0/100),0) | D21: =IFERROR(2/(1+9.0/100),0) | E21: =IFERROR(3/(1+9.0/100),0) | F21: =IFERROR(4/(1+9.0/100),0) | G21: =IFERROR(5/(1+9.0/100),0) | H21: =IFERROR(6/(1+9.0/100),0) | I21: =IFERROR(7/(1+9.0/100),0) | J21: =IFERROR(8/(1+9.0/100),0) | K21: =IFERROR(9/(1+9.0/100),0) | L21: =IFERROR(10/(1+9.0/100),0) | M21: =IFERROR(11/(1+9.0/100),0) | N21: =IFERROR(12/(1+9.0/100),0) | O21: =IFERROR(13/(1+9.0/100),0) | P21: =IFERROR(14/(1+9.0/100),0) | Q21: =IFERROR(15/(1+9.0/100),0)
B22: 9.25% | C22: =IFERROR(1/(1+9.25/100),0) | D22: =IFERROR(2/(1+9.25/100),0) | E22: =IFERROR(3/(1+9.25/100),0) | F22: =IFERROR(4/(1+9.25/100),0) | G22: =IFERROR(5/(1+9.25/100),0) | H22: =IFERROR(6/(1+9.25/100),0) | I22: =IFERROR(7/(1+9.25/100),0) | J22: =IFERROR(8/(1+9.25/100),0) | K22: =IFERROR(9/(1+9.25/100),0) | L22: =IFERROR(10/(1+9.25/100),0) | M22: =IFERROR(11/(1+9.25/100),0) | N22: =IFERROR(12/(1+9.25/100),0) | O22: =IFERROR(13/(1+9.25/100),0) | P22: =IFERROR(14/(1+9.25/100),0) | Q22: =IFERROR(15/(1+9.25/100),0)
B23: 9.50% | C23: =IFERROR(1/(1+9.5/100),0) | D23: =IFERROR(2/(1+9.5/100),0) | E23: =IFERROR(3/(1+9.5/100),0) | F23: =IFERROR(4/(1+9.5/100),0) | G23: =IFERROR(5/(1+9.5/100),0) | H23: =IFERROR(6/(1+9.5/100),0) | I23: =IFERROR(7/(1+9.5/100),0) | J23: =IFERROR(8/(1+9.5/100),0) | K23: =IFERROR(9/(1+9.5/100),0) | L23: =IFERROR(10/(1+9.5/100),0) | M23: =IFERROR(11/(1+9.5/100),0) | N23: =IFERROR(12/(1+9.5/100),0) | O23: =IFERROR(13/(1+9.5/100),0) | P23: =IFERROR(14/(1+9.5/100),0) | Q23: =IFERROR(15/(1+9.5/100),0)
B24: 9.75% | C24: =IFERROR(1/(1+9.75/100),0) | D24: =IFERROR(2/(1+9.75/100),0) | E24: =IFERROR(3/(1+9.75/100),0) | F24: =IFERROR(4/(1+9.75/100),0) | G24: =IFERROR(5/(1+9.75/100),0) | H24: =IFERROR(6/(1+9.75/100),0) | I24: =IFERROR(7/(1+9.75/100),0) | J24: =IFERROR(8/(1+9.75/100),0) | K24: =IFERROR(9/(1+9.75/100),0) | L24: =IFERROR(10/(1+9.75/100),0) | M24: =IFERROR(11/(1+9.75/100),0) | N24: =IFERROR(12/(1+9.75/100),0) | O24: =IFERROR(13/(1+9.75/100),0) | P24: =IFERROR(14/(1+9.75/100),0) | Q24: =IFERROR(15/(1+9.75/100),0)
B25: 10.00% | C25: =IFERROR(1/(1+10.0/100),0) | D25: =IFERROR(2/(1+10.0/100),0) | E25: =IFERROR(3/(1+10.0/100),0) | F25: =IFERROR(4/(1+10.0/100),0) | G25: =IFERROR(5/(1+10.0/100),0) | H25: =IFERROR(6/(1+10.0/100),0) | I25: =IFERROR(7/(1+10.0/100),0) | J25: =IFERROR(8/(1+10.0/100),0) | K25: =IFERROR(9/(1+10.0/100),0) | L25: =IFERROR(10/(1+10.0/100),0) | M25: =IFERROR(11/(1+10.0/100),0) | N25: =IFERROR(12/(1+10.0/100),0) | O25: =IFERROR(13/(1+10.0/100),0) | P25: =IFERROR(14/(1+10.0/100),0) | Q25: =IFERROR(15/(1+10.0/100),0)
B26: 10.25% | C26: =IFERROR(1/(1+10.25/100),0) | D26: =IFERROR(2/(1+10.25/100),0) | E26: =IFERROR(3/(1+10.25/100),0) | F26: =IFERROR(4/(1+10.25/100),0) | G26: =IFERROR(5/(1+10.25/100),0) | H26: =IFERROR(6/(1+10.25/100),0) | I26: =IFERROR(7/(1+10.25/100),0) | J26: =IFERROR(8/(1+10.25/100),0) | K26: =IFERROR(9/(1+10.25/100),0) | L26: =IFERROR(10/(1+10.25/100),0) | M26: =IFERROR(11/(1+10.25/100),0) | N26: =IFERROR(12/(1+10.25/100),0) | O26: =IFERROR(13/(1+10.25/100),0) | P26: =IFERROR(14/(1+10.25/100),0) | Q26: =IFERROR(15/(1+10.25/100),0)
B27: 10.50% | C27: =IFERROR(1/(1+10.5/100),0) | D27: =IFERROR(2/(1+10.5/100),0) | E27: =IFERROR(3/(1+10.5/100),0) | F27: =IFERROR(4/(1+10.5/100),0) | G27: =IFERROR(5/(1+10.5/100),0) | H27: =IFERROR(6/(1+10.5/100),0) | I27: =IFERROR(7/(1+10.5/100),0) | J27: =IFERROR(8/(1+10.5/100),0) | K27: =IFERROR(9/(1+10.5/100),0) | L27: =IFERROR(10/(1+10.5/100),0) | M27: =IFERROR(11/(1+10.5/100),0) | N27: =IFERROR(12/(1+10.5/100),0) | O27: =IFERROR(13/(1+10.5/100),0) | P27: =IFERROR(14/(1+10.5/100),0) | Q27: =IFERROR(15/(1+10.5/100),0)
B28: 10.75% | C28: =IFERROR(1/(1+10.75/100),0) | D28: =IFERROR(2/(1+10.75/100),0) | E28: =IFERROR(3/(1+10.75/100),0) | F28: =IFERROR(4/(1+10.75/100),0) | G28: =IFERROR(5/(1+10.75/100),0) | H28: =IFERROR(6/(1+10.75/100),0) | I28: =IFERROR(7/(1+10.75/100),0) | J28: =IFERROR(8/(1+10.75/100),0) | K28: =IFERROR(9/(1+10.75/100),0) | L28: =IFERROR(10/(1+10.75/100),0) | M28: =IFERROR(11/(1+10.75/100),0) | N28: =IFERROR(12/(1+10.75/100),0) | O28: =IFERROR(13/(1+10.75/100),0) | P28: =IFERROR(14/(1+10.75/100),0) | Q28: =IFERROR(15/(1+10.75/100),0)
B29: 11.00% | C29: =IFERROR(1/(1+11.0/100),0) | D29: =IFERROR(2/(1+11.0/100),0) | E29: =IFERROR(3/(1+11.0/100),0) | F29: =IFERROR(4/(1+11.0/100),0) | G29: =IFERROR(5/(1+11.0/100),0) | H29: =IFERROR(6/(1+11.0/100),0) | I29: =IFERROR(7/(1+11.0/100),0) | J29: =IFERROR(8/(1+11.0/100),0) | K29: =IFERROR(9/(1+11.0/100),0) | L29: =IFERROR(10/(1+11.0/100),0) | M29: =IFERROR(11/(1+11.0/100),0) | N29: =IFERROR(12/(1+11.0/100),0) | O29: =IFERROR(13/(1+11.0/100),0) | P29: =IFERROR(14/(1+11.0/100),0) | Q29: =IFERROR(15/(1+11.0/100),0)
B31: 📊 VBA Monte Carlo button (Import Macro button below) runs 10,000 yield path simulations and outputs VaR (95%) and CVaR at 99% confidence. Also plots histogram of price outcomes.
B33: 👇 IMPORT VBA MODULE: Developer → Visual Basic → File → Import File → select Duration_Model.bas from the repo. Then assign 'RunWhatIf' to a button.

Sheet Amort Schedule
B1: AMORTISATION SCHEDULE (FULL AMORT TYPE — REFERENCE)
B3: Period | C3: Opening Balance | D3: EMI / Coupon | E3: Interest Portion | F3: Principal Portion | G3: Closing Balance | H3: Cumulative Int.
B4: 1 | C4: =Inputs!C6 | D4: =IF(1<=Inputs!C10*Inputs!C8,Inputs!C6/(Inputs!C10*Inputs!C8)+Inputs!C6*Inputs!C7/Inputs!C8,0) | E4: =C4*Inputs!C7/Inputs!C8 | F4: =D4-E4 | G4: =C4-F4 | H4: =E4
B5: 2 | C5: =G4 | D5: =IF(2<=Inputs!C10*Inputs!C8,Inputs!C6/(Inputs!C10*Inputs!C8)+Inputs!C6*Inputs!C7/Inputs!C8,0) | E5: =C5*Inputs!C7/Inputs!C8 | F5: =D5-E5 | G5: =C5-F5 | H5: =G4+E5
B6: 3 | C6: =G5 | D6: =IF(3<=Inputs!C10*Inputs!C8,Inputs!C6/(Inputs!C10*Inputs!C8)+Inputs!C6*Inputs!C7/Inputs!C8,0) | E6: =C6*Inputs!C7/Inputs!C8 | F6: =D6-E6 | G6: =C6-F6 | H6: =G5+E6
B7: 4 | C7: =G6 | D7: =IF(4<=Inputs!C10*Inputs!C8,Inputs!C6/(Inputs!C10*Inputs!C8)+Inputs!C6*Inputs!C7/Inputs!C8,0) | E7: =C7*Inputs!C7/Inputs!C8 | F7: =D7-E7 | G7: =C7-F7 | H7: =G6+E7
B8: 5 | C8: =G7 | D8: =IF(5<=Inputs!C10*Inputs!C8,Inputs!C6/(Inputs!C10*Inputs!C8)+Inputs!C6*Inputs!C7/Inputs!C8,0) | E8: =C8*Inputs!C7/Inputs!C8 | F8: =D8-E8 | G8: =C8-F8 | H8: =G7+E8
B9: 6 | C9: =G8 | D9: =IF(6<=Inputs!C10*Inputs!C8,Inputs!C6/(Inputs!C10*Inputs!C8)+Inputs!C6*Inputs!C7/Inputs!C8,0) | E9: =C9*Inputs!C7/Inputs!C8 | F9: =D9-E9 | G9: =C9-F9 | H9: =G8+E9
B10: 7 | C10: =G9 | D10: =IF(7<=Inputs!C10*Inputs!C8,Inputs!C6/(Inputs!C10*Inputs!C8)+Inputs!C6*Inputs!C7/Inputs!C8,0) | E10: =C10*Inputs!C7/Inputs!C8 | F10: =D10-E10 | G10: =C10-F10 | H10: =G9+E10
B11: 8 | C11: =G10 | D11: =IF(8<=Inputs!C10*Inputs!C8,Inputs!C6/(Inputs!C10*Inputs!C8)+Inputs!C6*Inputs!C7/Inputs!C8,0) | E11: =C11*Inputs!C7/Inputs!C8 | F11: =D11-E11 | G11: =C11-F11 | H11: =G10+E11
B12: 9 | C12: =G11 | D12: =IF(9<=Inputs!C10*Inputs!C8,Inputs!C6/(Inputs!C10*Inputs!C8)+Inputs!C6*Inputs!C7/Inputs!C8,0) | E12: =C12*Inputs!C7/Inputs!C8 | F12: =D12-E12 | G12: =C12-F12 | H12: =G11+E12
B13: 10 | C13: =G12 | D13: =IF(10<=Inputs!C10*Inputs!C8,Inputs!C6/(Inputs!C10*Inputs!C8)+Inputs!C6*Inputs!C7/Inputs!C8,0) | E13: =C13*Inputs!C7/Inputs!C8 | F13: =D13-E13 | G13: =C13-F13 | H13: =G12+E13
B14: 11 | C14: =G13 | D14: =IF(11<=Inputs!C10*Inputs!C8,Inputs!C6/(Inputs!C10*Inputs!C8)+Inputs!C6*Inputs!C7/Inputs!C8,0) | E14: =C14*Inputs!C7/Inputs!C8 | F14: =D14-E14 | G14: =C14-F14 | H14: =G13+E14
B15: 12 | C15: =G14 | D15: =IF(12<=Inputs!C10*Inputs!C8,Inputs!C6/(Inputs!C10*Inputs!C8)+Inputs!C6*Inputs!C7/Inputs!C8,0) | E15: =C15*Inputs!C7/Inputs!C8 | F15: =D15-E15 | G15: =C15-F15 | H15: =G14+E15
B16: 13 | C16: =G15 | D16: =IF(13<=Inputs!C10*Inputs!C8,Inputs!C6/(Inputs!C10*Inputs!C8)+Inputs!C6*Inputs!C7/Inputs!C8,0) | E16: =C16*Inputs!C7/Inputs!C8 | F16: =D16-E16 | G16: =C16-F16 | H16: =G15+E16
B17: 14 | C17: =G16 | D17: =IF(14<=Inputs!C10*Inputs!C8,Inputs!C6/(Inputs!C10*Inputs!C8)+Inputs!C6*Inputs!C7/Inputs!C8,0) | E17: =C17*Inputs!C7/Inputs!C8 | F17: =D17-E17 | G17: =C17-F17 | H17: =G16+E17
B18: 15 | C18: =G17 | D18: =IF(15<=Inputs!C10*Inputs!C8,Inputs!C6/(Inputs!C10*Inputs!C8)+Inputs!C6*Inputs!C7/Inputs!C8,0) | E18: =C18*Inputs!C7/Inputs!C8 | F18: =D18-E18 | G18: =C18-F18 | H18: =G17+E18
B19: 16 | C19: =G18 | D19: =IF(16<=Inputs!C10*Inputs!C8,Inputs!C6/(Inputs!C10*Inputs!C8)+Inputs!C6*Inputs!C7/Inputs!C8,0) | E19: =C19*Inputs!C7/Inputs!C8 | F19: =D19-E19 | G19: =C19-F19 | H19: =G18+E19
B20: 17 | C20: =G19 | D20: =IF(17<=Inputs!C10*Inputs!C8,Inputs!C6/(Inputs!C10*Inputs!C8)+Inputs!C6*Inputs!C7/Inputs!C8,0) | E20: =C20*Inputs!C7/Inputs!C8 | F20: =D20-E20 | G20: =C20-F20 | H20: =G19+E20
B21: 18 | C21: =G20 | D21: =IF(18<=Inputs!C10*Inputs!C8,Inputs!C6/(Inputs!C10*Inputs!C8)+Inputs!C6*Inputs!C7/Inputs!C8,0) | E21: =C21*Inputs!C7/Inputs!C8 | F21: =D21-E21 | G21: =C21-F21 | H21: =G20+E21
B22: 19 | C22: =G21 | D22: =IF(19<=Inputs!C10*Inputs!C8,Inputs!C6/(Inputs!C10*Inputs!C8)+Inputs!C6*Inputs!C7/Inputs!C8,0) | E22: =C22*Inputs!C7/Inputs!C8 | F22: =D22-E22 | G22: =C22-F22 | H22: =G21+E22
B23: 20 | C23: =G22 | D23: =IF(20<=Inputs!C10*Inputs!C8,Inputs!C6/(Inputs!C10*Inputs!C8)+Inputs!C6*Inputs!C7/Inputs!C8,0) | E23: =C23*Inputs!C7/Inputs!C8 | F23: =D23-E23 | G23: =C23-F23 | H23: =G22+E23
B24: 21 | C24: =G23 | D24: =IF(21<=Inputs!C10*Inputs!C8,Inputs!C6/(Inputs!C10*Inputs!C8)+Inputs!C6*Inputs!C7/Inputs!C8,0) | E24: =C24*Inputs!C7/Inputs!C8 | F24: =D24-E24 | G24: =C24-F24 | H24: =G23+E24
B25: 22 | C25: =G24 | D25: =IF(22<=Inputs!C10*Inputs!C8,Inputs!C6/(Inputs!C10*Inputs!C8)+Inputs!C6*Inputs!C7/Inputs!C8,0) | E25: =C25*Inputs!C7/Inputs!C8 | F25: =D25-E25 | G25: =C25-F25 | H25: =G24+E25
B26: 23 | C26: =G25 | D26: =IF(23<=Inputs!C10*Inputs!C8,Inputs!C6/(Inputs!C10*Inputs!C8)+Inputs!C6*Inputs!C7/Inputs!C8,0) | E26: =C26*Inputs!C7/Inputs!C8 | F26: =D26-E26 | G26: =C26-F26 | H26: =G25+E26
B27: 24 | C27: =G26 | D27: =IF(24<=Inputs!C10*Inputs!C8,Inputs!C6/(Inputs!C10*Inputs!C8)+Inputs!C6*Inputs!C7/Inputs!C8,0) | E27: =C27*Inputs!C7/Inputs!C8 | F27: =D27-E27 | G27: =C27-F27 | H27: =G26+E27
B28: 25 | C28: =G27 | D28: =IF(25<=Inputs!C10*Inputs!C8,Inputs!C6/(Inputs!C10*Inputs!C8)+Inputs!C6*Inputs!C7/Inputs!C8,0) | E28: =C28*Inputs!C7/Inputs!C8 | F28: =D28-E28 | G28: =C28-F28 | H28: =G27+E28
B29: 26 | C29: =G28 | D29: =IF(26<=Inputs!C10*Inputs!C8,Inputs!C6/(Inputs!C10*Inputs!C8)+Inputs!C6*Inputs!C7/Inputs!C8,0) | E29: =C29*Inputs!C7/Inputs!C8 | F29: =D29-E29 | G29: =C29-F29 | H29: =G28+E29
B30: 27 | C30: =G29 | D30: =IF(27<=Inputs!C10*Inputs!C8,Inputs!C6/(Inputs!C10*Inputs!C8)+Inputs!C6*Inputs!C7/Inputs!C8,0) | E30: =C30*Inputs!C7/Inputs!C8 | F30: =D30-E30 | G30: =C30-F30 | H30: =G29+E30
B31: 28 | C31: =G30 | D31: =IF(28<=Inputs!C10*Inputs!C8,Inputs!C6/(Inputs!C10*Inputs!C8)+Inputs!C6*Inputs!C7/Inputs!C8,0) | E31: =C31*Inputs!C7/Inputs!C8 | F31: =D31-E31 | G31: =C31-F31 | H31: =G30+E31
B32: 29 | C32: =G31 | D32: =IF(29<=Inputs!C10*Inputs!C8,Inputs!C6/(Inputs!C10*Inputs!C8)+Inputs!C6*Inputs!C7/Inputs!C8,0) | E32: =C32*Inputs!C7/Inputs!C8 | F32: =D32-E32 | G32: =C32-F32 | H32: =G31+E32
B33: 30 | C33: =G32 | D33: =IF(30<=Inputs!C10*Inputs!C8,Inputs!C6/(Inputs!C10*Inputs!C8)+Inputs!C6*Inputs!C7/Inputs!C8,0) | E33: =C33*Inputs!C7/Inputs!C8 | F33: =D33-E33 | G33: =C33-F33 | H33: =G32+E33
B34: 31 | C34: =G33 | D34: =IF(31<=Inputs!C10*Inputs!C8,Inputs!C6/(Inputs!C10*Inputs!C8)+Inputs!C6*Inputs!C7/Inputs!C8,0) | E34: =C34*Inputs!C7/Inputs!C8 | F34: =D34-E34 | G34: =C34-F34 | H34: =G33+E34
B35: 32 | C35: =G34 | D35: =IF(32<=Inputs!C10*Inputs!C8,Inputs!C6/(Inputs!C10*Inputs!C8)+Inputs!C6*Inputs!C7/Inputs!C8,0) | E35: =C35*Inputs!C7/Inputs!C8 | F35: =D35-E35 | G35: =C35-F35 | H35: =G34+E35
B36: 33 | C36: =G35 | D36: =IF(33<=Inputs!C10*Inputs!C8,Inputs!C6/(Inputs!C10*Inputs!C8)+Inputs!C6*Inputs!C7/Inputs!C8,0) | E36: =C36*Inputs!C7/Inputs!C8 | F36: =D36-E36 | G36: =C36-F36 | H36: =G35+E36
B37: 34 | C37: =G36 | D37: =IF(34<=Inputs!C10*Inputs!C8,Inputs!C6/(Inputs!C10*Inputs!C8)+Inputs!C6*Inputs!C7/Inputs!C8,0) | E37: =C37*Inputs!C7/Inputs!C8 | F37: =D37-E37 | G37: =C37-F37 | H37: =G36+E37
B38: 35 | C38: =G37 | D38: =IF(35<=Inputs!C10*Inputs!C8,Inputs!C6/(Inputs!C10*Inputs!C8)+Inputs!C6*Inputs!C7/Inputs!C8,0) | E38: =C38*Inputs!C7/Inputs!C8 | F38: =D38-E38 | G38: =C38-F38 | H38: =G37+E38
B39: 36 | C39: =G38 | D39: =IF(36<=Inputs!C10*Inputs!C8,Inputs!C6/(Inputs!C10*Inputs!C8)+Inputs!C6*Inputs!C7/Inputs!C8,0) | E39: =C39*Inputs!C7/Inputs!C8 | F39: =D39-E39 | G39: =C39-F39 | H39: =G38+E39
B40: 37 | C40: =G39 | D40: =IF(37<=Inputs!C10*Inputs!C8,Inputs!C6/(Inputs!C10*Inputs!C8)+Inputs!C6*Inputs!C7/Inputs!C8,0) | E40: =C40*Inputs!C7/Inputs!C8 | F40: =D40-E40 | G40: =C40-F40 | H40: =G39+E40
B41: 38 | C41: =G40 | D41: =IF(38<=Inputs!C10*Inputs!C8,Inputs!C6/(Inputs!C10*Inputs!C8)+Inputs!C6*Inputs!C7/Inputs!C8,0) | E41: =C41*Inputs!C7/Inputs!C8 | F41: =D41-E41 | G41: =C41-F41 | H41: =G40+E41
B42: 39 | C42: =G41 | D42: =IF(39<=Inputs!C10*Inputs!C8,Inputs!C6/(Inputs!C10*Inputs!C8)+Inputs!C6*Inputs!C7/Inputs!C8,0) | E42: =C42*Inputs!C7/Inputs!C8 | F42: =D42-E42 | G42: =C42-F42 | H42: =G41+E42
B43: 40 | C43: =G42 | D43: =IF(40<=Inputs!C10*Inputs!C8,Inputs!C6/(Inputs!C10*Inputs!C8)+Inputs!C6*Inputs!C7/Inputs!C8,0) | E43: =C43*Inputs!C7/Inputs!C8 | F43: =D43-E43 | G43: =C43-F43 | H43: =G42+E43
B44: 41 | C44: =G43 | D44: =IF(41<=Inputs!C10*Inputs!C8,Inputs!C6/(Inputs!C10*Inputs!C8)+Inputs!C6*Inputs!C7/Inputs!C8,0) | E44: =C44*Inputs!C7/Inputs!C8 | F44: =D44-E44 | G44: =C44-F44 | H44: =G43+E44
B45: 42 | C45: =G44 | D45: =IF(42<=Inputs!C10*Inputs!C8,Inputs!C6/(Inputs!C10*Inputs!C8)+Inputs!C6*Inputs!C7/Inputs!C8,0) | E45: =C45*Inputs!C7/Inputs!C8 | F45: =D45-E45 | G45: =C45-F45 | H45: =G44+E45
B46: 43 | C46: =G45 | D46: =IF(43<=Inputs!C10*Inputs!C8,Inputs!C6/(Inputs!C10*Inputs!C8)+Inputs!C6*Inputs!C7/Inputs!C8,0) | E46: =C46*Inputs!C7/Inputs!C8 | F46: =D46-E46 | G46: =C46-F46 | H46: =G45+E46
B47: 44 | C47: =G46 | D47: =IF(44<=Inputs!C10*Inputs!C8,Inputs!C6/(Inputs!C10*Inputs!C8)+Inputs!C6*Inputs!C7/Inputs!C8,0) | E47: =C47*Inputs!C7/Inputs!C8 | F47: =D47-E47 | G47: =C47-F47 | H47: =G46+E47
B48: 45 | C48: =G47 | D48: =IF(45<=Inputs!C10*Inputs!C8,Inputs!C6/(Inputs!C10*Inputs!C8)+Inputs!C6*Inputs!C7/Inputs!C8,0) | E48: =C48*Inputs!C7/Inputs!C8 | F48: =D48-E48 | G48: =C48-F48 | H48: =G47+E48
B49: 46 | C49: =G48 | D49: =IF(46<=Inputs!C10*Inputs!C8,Inputs!C6/(Inputs!C10*Inputs!C8)+Inputs!C6*Inputs!C7/Inputs!C8,0) | E49: =C49*Inputs!C7/Inputs!C8 | F49: =D49-E49 | G49: =C49-F49 | H49: =G48+E49
B50: 47 | C50: =G49 | D50: =IF(47<=Inputs!C10*Inputs!C8,Inputs!C6/(Inputs!C10*Inputs!C8)+Inputs!C6*Inputs!C7/Inputs!C8,0) | E50: =C50*Inputs!C7/Inputs!C8 | F50: =D50-E50 | G50: =C50-F50 | H50: =G49+E50
B51: 48 | C51: =G50 | D51: =IF(48<=Inputs!C10*Inputs!C8,Inputs!C6/(Inputs!C10*Inputs!C8)+Inputs!C6*Inputs!C7/Inputs!C8,0) | E51: =C51*Inputs!C7/Inputs!C8 | F51: =D51-E51 | G51: =C51-F51 | H51: =G50+E51
B52: 49 | C52: =G51 | D52: =IF(49<=Inputs!C10*Inputs!C8,Inputs!C6/(Inputs!C10*Inputs!C8)+Inputs!C6*Inputs!C7/Inputs!C8,0) | E52: =C52*Inputs!C7/Inputs!C8 | F52: =D52-E52 | G52: =C52-F52 | H52: =G51+E52
B53: 50 | C53: =G52 | D53: =IF(50<=Inputs!C10*Inputs!C8,Inputs!C6/(Inputs!C10*Inputs!C8)+Inputs!C6*Inputs!C7/Inputs!C8,0) | E53: =C53*Inputs!C7/Inputs!C8 | F53: =D53-E53 | G53: =C53-F53 | H53: =G52+E53
B54: 51 | C54: =G53 | D54: =IF(51<=Inputs!C10*Inputs!C8,Inputs!C6/(Inputs!C10*Inputs!C8)+Inputs!C6*Inputs!C7/Inputs!C8,0) | E54: =C54*Inputs!C7/Inputs!C8 | F54: =D54-E54 | G54: =C54-F54 | H54: =G53+E54
B55: 52 | C55: =G54 | D55: =IF(52<=Inputs!C10*Inputs!C8,Inputs!C6/(Inputs!C10*Inputs!C8)+Inputs!C6*Inputs!C7/Inputs!C8,0) | E55: =C55*Inputs!C7/Inputs!C8 | F55: =D55-E55 | G55: =C55-F55 | H55: =G54+E55
B56: 53 | C56: =G55 | D56: =IF(53<=Inputs!C10*Inputs!C8,Inputs!C6/(Inputs!C10*Inputs!C8)+Inputs!C6*Inputs!C7/Inputs!C8,0) | E56: =C56*Inputs!C7/Inputs!C8 | F56: =D56-E56 | G56: =C56-F56 | H56: =G55+E56
B57: 54 | C57: =G56 | D57: =IF(54<=Inputs!C10*Inputs!C8,Inputs!C6/(Inputs!C10*Inputs!C8)+Inputs!C6*Inputs!C7/Inputs!C8,0) | E57: =C57*Inputs!C7/Inputs!C8 | F57: =D57-E57 | G57: =C57-F57 | H57: =G56+E57
B58: 55 | C58: =G57 | D58: =IF(55<=Inputs!C10*Inputs!C8,Inputs!C6/(Inputs!C10*Inputs!C8)+Inputs!C6*Inputs!C7/Inputs!C8,0) | E58: =C58*Inputs!C7/Inputs!C8 | F58: =D58-E58 | G58: =C58-F58 | H58: =G57+E58
B59: 56 | C59: =G58 | D59: =IF(56<=Inputs!C10*Inputs!C8,Inputs!C6/(Inputs!C10*Inputs!C8)+Inputs!C6*Inputs!C7/Inputs!C8,0) | E59: =C59*Inputs!C7/Inputs!C8 | F59: =D59-E59 | G59: =C59-F59 | H59: =G58+E59
B60: 57 | C60: =G59 | D60: =IF(57<=Inputs!C10*Inputs!C8,Inputs!C6/(Inputs!C10*Inputs!C8)+Inputs!C6*Inputs!C7/Inputs!C8,0) | E60: =C60*Inputs!C7/Inputs!C8 | F60: =D60-E60 | G60: =C60-F60 | H60: =G59+E60
B61: 58 | C61: =G60 | D61: =IF(58<=Inputs!C10*Inputs!C8,Inputs!C6/(Inputs!C10*Inputs!C8)+Inputs!C6*Inputs!C7/Inputs!C8,0) | E61: =C61*Inputs!C7/Inputs!C8 | F61: =D61-E61 | G61: =C61-F61 | H61: =G60+E61
B62: 59 | C62: =G61 | D62: =IF(59<=Inputs!C10*Inputs!C8,Inputs!C6/(Inputs!C10*Inputs!C8)+Inputs!C6*Inputs!C7/Inputs!C8,0) | E62: =C62*Inputs!C7/Inputs!C8 | F62: =D62-E62 | G62: =C62-F62 | H62: =G61+E62
B63: 60 | C63: =G62 | D63: =IF(60<=Inputs!C10*Inputs!C8,Inputs!C6/(Inputs!C10*Inputs!C8)+Inputs!C6*Inputs!C7/Inputs!C8,0) | E63: =C63*Inputs!C7/Inputs!C8 | F63: =D63-E63 | G63: =C63-F63 | H63: =G62+E63
B64: 61 | C64: =G63 | D64: =IF(61<=Inputs!C10*Inputs!C8,Inputs!C6/(Inputs!C10*Inputs!C8)+Inputs!C6*Inputs!C7/Inputs!C8,0) | E64: =C64*Inputs!C7/Inputs!C8 | F64: =D64-E64 | G64: =C64-F64 | H64: =G63+E64
B65: 62 | C65: =G64 | D65: =IF(62<=Inputs!C10*Inputs!C8,Inputs!C6/(Inputs!C10*Inputs!C8)+Inputs!C6*Inputs!C7/Inputs!C8,0) | E65: =C65*Inputs!C7/Inputs!C8 | F65: =D65-E65 | G65: =C65-F65 | H65: =G64+E65
B66: 63 | C66: =G65 | D66: =IF(63<=Inputs!C10*Inputs!C8,Inputs!C6/(Inputs!C10*Inputs!C8)+Inputs!C6*Inputs!C7/Inputs!C8,0) | E66: =C66*Inputs!C7/Inputs!C8 | F66: =D66-E66 | G66: =C66-F66 | H66: =G65+E66
B67: 64 | C67: =G66 | D67: =IF(64<=Inputs!C10*Inputs!C8,Inputs!C6/(Inputs!C10*Inputs!C8)+Inputs!C6*Inputs!C7/Inputs!C8,0) | E67: =C67*Inputs!C7/Inputs!C8 | F67: =D67-E67 | G67: =C67-F67 | H67: =G66+E67
B68: 65 | C68: =G67 | D68: =IF(65<=Inputs!C10*Inputs!C8,Inputs!C6/(Inputs!C10*Inputs!C8)+Inputs!C6*Inputs!C7/Inputs!C8,0) | E68: =C68*Inputs!C7/Inputs!C8 | F68: =D68-E68 | G68: =C68-F68 | H68: =G67+E68
B69: 66 | C69: =G68 | D69: =IF(66<=Inputs!C10*Inputs!C8,Inputs!C6/(Inputs!C10*Inputs!C8)+Inputs!C6*Inputs!C7/Inputs!C8,0) | E69: =C69*Inputs!C7/Inputs!C8 | F69: =D69-E69 | G69: =C69-F69 | H69: =G68+E69
B70: 67 | C70: =G69 | D70: =IF(67<=Inputs!C10*Inputs!C8,Inputs!C6/(Inputs!C10*Inputs!C8)+Inputs!C6*Inputs!C7/Inputs!C8,0) | E70: =C70*Inputs!C7/Inputs!C8 | F70: =D70-E70 | G70: =C70-F70 | H70: =G69+E70
B71: 68 | C71: =G70 | D71: =IF(68<=Inputs!C10*Inputs!C8,Inputs!C6/(Inputs!C10*Inputs!C8)+Inputs!C6*Inputs!C7/Inputs!C8,0) | E71: =C71*Inputs!C7/Inputs!C8 | F71: =D71-E71 | G71: =C71-F71 | H71: =G70+E71
B72: 69 | C72: =G71 | D72: =IF(69<=Inputs!C10*Inputs!C8,Inputs!C6/(Inputs!C10*Inputs!C8)+Inputs!C6*Inputs!C7/Inputs!C8,0) | E72: =C72*Inputs!C7/Inputs!C8 | F72: =D72-E72 | G72: =C72-F72 | H72: =G71+E72
B73: 70 | C73: =G72 | D73: =IF(70<=Inputs!C10*Inputs!C8,Inputs!C6/(Inputs!C10*Inputs!C8)+Inputs!C6*Inputs!C7/Inputs!C8,0) | E73: =C73*Inputs!C7/Inputs!C8 | F73: =D73-E73 | G73: =C73-F73 | H73: =G72+E73
B74: 71 | C74: =G73 | D74: =IF(71<=Inputs!C10*Inputs!C8,Inputs!C6/(Inputs!C10*Inputs!C8)+Inputs!C6*Inputs!C7/Inputs!C8,0) | E74: =C74*Inputs!C7/Inputs!C8 | F74: =D74-E74 | G74: =C74-F74 | H74: =G73+E74
B75: 72 | C75: =G74 | D75: =IF(72<=Inputs!C10*Inputs!C8,Inputs!C6/(Inputs!C10*Inputs!C8)+Inputs!C6*Inputs!C7/Inputs!C8,0) | E75: =C75*Inputs!C7/Inputs!C8 | F75: =D75-E75 | G75: =C75-F75 | H75: =G74+E75
B76: 73 | C76: =G75 | D76: =IF(73<=Inputs!C10*Inputs!C8,Inputs!C6/(Inputs!C10*Inputs!C8)+Inputs!C6*Inputs!C7/Inputs!C8,0) | E76: =C76*Inputs!C7/Inputs!C8 | F76: =D76-E76 | G76: =C76-F76 | H76: =G75+E76
B77: 74 | C77: =G76 | D77: =IF(74<=Inputs!C10*Inputs!C8,Inputs!C6/(Inputs!C10*Inputs!C8)+Inputs!C6*Inputs!C7/Inputs!C8,0) | E77: =C77*Inputs!C7/Inputs!C8 | F77: =D77-E77 | G77: =C77-F77 | H77: =G76+E77
B78: 75 | C78: =G77 | D78: =IF(75<=Inputs!C10*Inputs!C8,Inputs!C6/(Inputs!C10*Inputs!C8)+Inputs!C6*Inputs!C7/Inputs!C8,0) | E78: =C78*Inputs!C7/Inputs!C8 | F78: =D78-E78 | G78: =C78-F78 | H78: =G77+E78
B79: 76 | C79: =G78 | D79: =IF(76<=Inputs!C10*Inputs!C8,Inputs!C6/(Inputs!C10*Inputs!C8)+Inputs!C6*Inputs!C7/Inputs!C8,0) | E79: =C79*Inputs!C7/Inputs!C8 | F79: =D79-E79 | G79: =C79-F79 | H79: =G78+E79
B80: 77 | C80: =G79 | D80: =IF(77<=Inputs!C10*Inputs!C8,Inputs!C6/(Inputs!C10*Inputs!C8)+Inputs!C6*Inputs!C7/Inputs!C8,0) | E80: =C80*Inputs!C7/Inputs!C8 | F80: =D80-E80 | G80: =C80-F80 | H80: =G79+E80
B81: 78 | C81: =G80 | D81: =IF(78<=Inputs!C10*Inputs!C8,Inputs!C6/(Inputs!C10*Inputs!C8)+Inputs!C6*Inputs!C7/Inputs!C8,0) | E81: =C81*Inputs!C7/Inputs!C8 | F81: =D81-E81 | G81: =C81-F81 | H81: =G80+E81
B82: 79 | C82: =G81 | D82: =IF(79<=Inputs!C10*Inputs!C8,Inputs!C6/(Inputs!C10*Inputs!C8)+Inputs!C6*Inputs!C7/Inputs!C8,0) | E82: =C82*Inputs!C7/Inputs!C8 | F82: =D82-E82 | G82: =C82-F82 | H82: =G81+E82
B83: 80 | C83: =G82 | D83: =IF(80<=Inputs!C10*Inputs!C8,Inputs!C6/(Inputs!C10*Inputs!C8)+Inputs!C6*Inputs!C7/Inputs!C8,0) | E83: =C83*Inputs!C7/Inputs!C8 | F83: =D83-E83 | G83: =C83-F83 | H83: =G82+E83
B84: 81 | C84: =G83 | D84: =IF(81<=Inputs!C10*Inputs!C8,Inputs!C6/(Inputs!C10*Inputs!C8)+Inputs!C6*Inputs!C7/Inputs!C8,0) | E84: =C84*Inputs!C7/Inputs!C8 | F84: =D84-E84 | G84: =C84-F84 | H84: =G83+E84
B85: 82 | C85: =G84 | D85: =IF(82<=Inputs!C10*Inputs!C8,Inputs!C6/(Inputs!C10*Inputs!C8)+Inputs!C6*Inputs!C7/Inputs!C8,0) | E85: =C85*Inputs!C7/Inputs!C8 | F85: =D85-E85 | G85: =C85-F85 | H85: =G84+E85
B86: 83 | C86: =G85 | D86: =IF(83<=Inputs!C10*Inputs!C8,Inputs!C6/(Inputs!C10*Inputs!C8)+Inputs!C6*Inputs!C7/Inputs!C8,0) | E86: =C86*Inputs!C7/Inputs!C8 | F86: =D86-E86 | G86: =C86-F86 | H86: =G85+E86
B87: 84 | C87: =G86 | D87: =IF(84<=Inputs!C10*Inputs!C8,Inputs!C6/(Inputs!C10*Inputs!C8)+Inputs!C6*Inputs!C7/Inputs!C8,0) | E87: =C87*Inputs!C7/Inputs!C8 | F87: =D87-E87 | G87: =C87-F87 | H87: =G86+E87
B88: 85 | C88: =G87 | D88: =IF(85<=Inputs!C10*Inputs!C8,Inputs!C6/(Inputs!C10*Inputs!C8)+Inputs!C6*Inputs!C7/Inputs!C8,0) | E88: =C88*Inputs!C7/Inputs!C8 | F88: =D88-E88 | G88: =C88-F88 | H88: =G87+E88
B89: 86 | C89: =G88 | D89: =IF(86<=Inputs!C10*Inputs!C8,Inputs!C6/(Inputs!C10*Inputs!C8)+Inputs!C6*Inputs!C7/Inputs!C8,0) | E89: =C89*Inputs!C7/Inputs!C8 | F89: =D89-E89 | G89: =C89-F89 | H89: =G88+E89
B90: 87 | C90: =G89 | D90: =IF(87<=Inputs!C10*Inputs!C8,Inputs!C6/(Inputs!C10*Inputs!C8)+Inputs!C6*Inputs!C7/Inputs!C8,0) | E90: =C90*Inputs!C7/Inputs!C8 | F90: =D90-E90 | G90: =C90-F90 | H90: =G89+E90
B91: 88 | C91: =G90 | D91: =IF(88<=Inputs!C10*Inputs!C8,Inputs!C6/(Inputs!C10*Inputs!C8)+Inputs!C6*Inputs!C7/Inputs!C8,0) | E91: =C91*Inputs!C7/Inputs!C8 | F91: =D91-E91 | G91: =C91-F91 | H91: =G90+E91
B92: 89 | C92: =G91 | D92: =IF(89<=Inputs!C10*Inputs!C8,Inputs!C6/(Inputs!C10*Inputs!C8)+Inputs!C6*Inputs!C7/Inputs!C8,0) | E92: =C92*Inputs!C7/Inputs!C8 | F92: =D92-E92 | G92: =C92-F92 | H92: =G91+E92
B93: 90 | C93: =G92 | D93: =IF(90<=Inputs!C10*Inputs!C8,Inputs!C6/(Inputs!C10*Inputs!C8)+Inputs!C6*Inputs!C7/Inputs!C8,0) | E93: =C93*Inputs!C7/Inputs!C8 | F93: =D93-E93 | G93: =C93-F93 | H93: =G92+E93
B94: 91 | C94: =G93 | D94: =IF(91<=Inputs!C10*Inputs!C8,Inputs!C6/(Inputs!C10*Inputs!C8)+Inputs!C6*Inputs!C7/Inputs!C8,0) | E94: =C94*Inputs!C7/Inputs!C8 | F94: =D94-E94 | G94: =C94-F94 | H94: =G93+E94
B95: 92 | C95: =G94 | D95: =IF(92<=Inputs!C10*Inputs!C8,Inputs!C6/(Inputs!C10*Inputs!C8)+Inputs!C6*Inputs!C7/Inputs!C8,0) | E95: =C95*Inputs!C7/Inputs!C8 | F95: =D95-E95 | G95: =C95-F95 | H95: =G94+E95
B96: 93 | C96: =G95 | D96: =IF(93<=Inputs!C10*Inputs!C8,Inputs!C6/(Inputs!C10*Inputs!C8)+Inputs!C6*Inputs!C7/Inputs!C8,0) | E96: =C96*Inputs!C7/Inputs!C8 | F96: =D96-E96 | G96: =C96-F96 | H96: =G95+E96
B97: 94 | C97: =G96 | D97: =IF(94<=Inputs!C10*Inputs!C8,Inputs!C6/(Inputs!C10*Inputs!C8)+Inputs!C6*Inputs!C7/Inputs!C8,0) | E97: =C97*Inputs!C7/Inputs!C8 | F97: =D97-E97 | G97: =C97-F97 | H97: =G96+E97
B98: 95 | C98: =G97 | D98: =IF(95<=Inputs!C10*Inputs!C8,Inputs!C6/(Inputs!C10*Inputs!C8)+Inputs!C6*Inputs!C7/Inputs!C8,0) | E98: =C98*Inputs!C7/Inputs!C8 | F98: =D98-E98 | G98: =C98-F98 | H98: =G97+E98
B99: 96 | C99: =G98 | D99: =IF(96<=Inputs!C10*Inputs!C8,Inputs!C6/(Inputs!C10*Inputs!C8)+Inputs!C6*Inputs!C7/Inputs!C8,0) | E99: =C99*Inputs!C7/Inputs!C8 | F99: =D99-E99 | G99: =C99-F99 | H99: =G98+E99
B100: 97 | C100: =G99 | D100: =IF(97<=Inputs!C10*Inputs!C8,Inputs!C6/(Inputs!C10*Inputs!C8)+Inputs!C6*Inputs!C7/Inputs!C8,0) | E100: =C100*Inputs!C7/Inputs!C8 | F100: =D100-E100 | G100: =C100-F100 | H100: =G99+E100
B101: 98 | C101: =G100 | D101: =IF(98<=Inputs!C10*Inputs!C8,Inputs!C6/(Inputs!C10*Inputs!C8)+Inputs!C6*Inputs!C7/Inputs!C8,0) | E101: =C101*Inputs!C7/Inputs!C8 | F101: =D101-E101 | G101: =C101-F101 | H101: =G100+E101
...
